Workbook

Sheet TABLE
F2: 1 MODULE
F4: Table format | S4: POINTS TO BE NOTED
B6: TABLE FORMAT | L6: RANGE FORMAT
S7: DATA SORTING = in table
B8: CLASS 10TH STUDENTS | L8: CLASS 10TH STUDENTS
B9: S.NO | C9: Name | D9: English | E9: Maths | F9: Science | G9: Hindi | L9: S.NO | M9: Name | N9: English | O9: Maths | P9: Science | Q9: Hindi
B10: 1 | C10: Aarav Sharma | D10: 85 | E10: 47 | F10: 22 | G10: 39 | L10: 1 | M10: Aarav Sharma | N10: 85 | O10: 47 | P10: 22 | Q10: 39
B11: 2 | C11: Aditi Mehta | D11: 92 | E11: 33 | F11: 56 | G11: 78 | L11: 2 | M11: Aditi Mehta | N11: 92 | O11: 33 | P11: 56 | Q11: 78
B12: 3 | C12: Rohan Kumar | D12: 78 | E12: 15 | F12: 91 | G12: 64 | L12: 3 | M12: Rohan Kumar | N12: 78 | O12: 15 | P12: 91 | Q12: 64
B13: 4 | C13: Isha Patel | D13: 88 | E13: 29 | F13: 43 | G13: 50 | L13: 4 | M13: Isha Patel | O13: 29 | P13: 43 | Q13: 50
B14: 5 | C14: Anaya Gupta | D14: 95 | E14: 67 | F14: 85 | G14: 19 | L14: 5 | M14: Anaya Gupta | N14: 95 | O14: 67 | P14: 85 | Q14: 19
B15: 6 | C15: Aryan Singh | D15: 81 | E15: 24 | F15: 72 | G15: 88 | L15: 6 | M15: Aryan Singh | N15: 81 | O15: 24 | P15: 72 | Q15: 88
B16: 7 | C16: Neha Reddy | D16: 89 | E16: 31 | F16: 18 | G16: 75 | L16: 7 | M16: Neha Reddy | N16: 89 | O16: 31 | P16: 18 | Q16: 75
B17: 8 | C17: Kabir Joshi | D17: 76 | E17: 58 | F17: 92 | G17: 13 | L17: 8 | M17: Kabir Joshi | N17: 76 | O17: 58 | P17: 92 | Q17: 13
B18: 9 | C18: Sneha Desai | D18: 91 | E18: 44 | F18: 38 | G18: 61 | L18: 9 | M18: Sneha Desai | N18: 91 | O18: 44 | P18: 38 | Q18: 61
B19: 10 | C19: Vihaan Rao | D19: 84 | E19: 76 | F19: 53 | G19: 27 | L19: 10 | M19: Vihaan Rao | N19: 84 | O19: 76 | P19: 53 | Q19: 27
H23: LOGICAL CALCULATION
H25: FIND OUT DAYS WE LIVE ON EARTH
H27: We only know | I27: CURRENT DATE | J27: DATE OF BIRTH | K27: Days we live on earth (FIND)
H28: DATE | I28: =TODAY() -> 45722 | J28: 26523 | K28: =I28-J28 -> 19199
H31: We only know | I31: CURRENT DATE | J31: Days we live on earth | K31: DATE OF BIRTH (FIND)
H32: Days | I32: =TODAY() -> 45722 | J32: 6386 | K32: =I32-J32 -> 39336
H35: We only know | I35: Total days | J35: Hours we lived on earth(F) | K35: Minutes we live on earth(F)
H36: Days | I36: 19170 | J36: =I36*24 -> 460080 | K36: =J36*60 -> 27604800
H39: We only know | I39: Total days | J39: Age of a Person
H40: Days | I40: 4078 | J40: =INT(I40/365.5) -> 11
H42: We only know | I42: DATE OF BIRTH | J42: Age of a Person
H43: DATE OF BIRTH | I43: 26523 | J43: =INT((TODAY()-I43)/365.5) -> 52

Sheet PASTE SPECIAL
G2: 2 MODULE
G4: Paste special function | R4: POINTS TO BE NOTED
D6: FN RANDOMBETWEEN (VARIABLE) | K6: FN RANDOMBETWEEN (Constant)
R7: fn = function
C8: =RANDBETWEEN(30,500) -> 276 | D8: =RANDBETWEEN(30,500) -> 131 | E8: =RANDBETWEEN(30,500) -> 424 | F8: =RANDBETWEEN(30,500) -> 120 | G8: =RANDBETWEEN(30,500) -> 457 | H8: =RANDBETWEEN(30,500) -> 247 | J8: 249 | K8: 171 | L8: 458 | M8: 150 | N8: 303 | O8: 308
C9: =RANDBETWEEN(30,500) -> 373 | D9: =RANDBETWEEN(30,500) -> 241 | E9: =RANDBETWEEN(30,500) -> 329 | F9: =RANDBETWEEN(30,500) -> 57 | G9: =RANDBETWEEN(30,500) -> 395 | H9: =RANDBETWEEN(30,500) -> 492 | J9: 282 | K9: 280 | L9: 80 | M9: 259 | N9: 68 | O9: 271 | R9: to make constant used paste special
C10: =RANDBETWEEN(30,500) -> 304 | D10: =RANDBETWEEN(30,500) -> 290 | E10: =RANDBETWEEN(30,500) -> 366 | F10: =RANDBETWEEN(30,500) -> 32 | G10: =RANDBETWEEN(30,500) -> 315 | H10: =RANDBETWEEN(30,500) -> 131 | J10: 339 | K10: 171 | L10: 51 | M10: 380 | N10: 122 | O10: 494 | R10: Paste shortcut = ctrl + alt + v
C11: =RANDBETWEEN(30,500) -> 318 | D11: =RANDBETWEEN(30,500) -> 320 | E11: =RANDBETWEEN(30,500) -> 440 | F11: =RANDBETWEEN(30,500) -> 428 | G11: =RANDBETWEEN(30,500) -> 49 | H11: =RANDBETWEEN(30,500) -> 447 | J11: 307 | K11: 76 | L11: 144 | M11: 44 | N11: 440 | O11: 429
C12: =RANDBETWEEN(30,500) -> 276 | D12: =RANDBETWEEN(30,500) -> 381 | E12: =RANDBETWEEN(30,500) -> 331 | F12: =RANDBETWEEN(30,500) -> 160 | G12: =RANDBETWEEN(30,500) -> 374 | H12: =RANDBETWEEN(30,500) -> 345 | J12: 454 | K12: 47 | L12: 163 | M12: 82 | N12: 325 | O12: 96 | R12: Go to shortcut = ctrl + g
C13: =RANDBETWEEN(30,500) -> 394 | D13: =RANDBETWEEN(30,500) -> 421 | E13: =RANDBETWEEN(30,500) -> 386 | F13: =RANDBETWEEN(30,500) -> 415 | G13: =RANDBETWEEN(30,500) -> 213 | H13: =RANDBETWEEN(30,500) -> 257 | J13: 228 | K13: 77 | L13: 398 | M13: 244 | N13: 123 | O13: 38 | R13: [Go to] fn helps in finding require cell
C14: =RANDBETWEEN(30,500) -> 119 | D14: =RANDBETWEEN(30,500) -> 473 | E14: =RANDBETWEEN(30,500) -> 423 | F14: =RANDBETWEEN(30,500) -> 236 | G14: =RANDBETWEEN(30,500) -> 83 | H14: =RANDBETWEEN(30,500) -> 392 | J14: 72 | K14: 107 | L14: 238 | M14: 237 | N14: 160 | O14: 334
C15: =RANDBETWEEN(30,500) -> 54 | D15: =RANDBETWEEN(30,500) -> 293 | E15: =RANDBETWEEN(30,500) -> 343 | F15: =RANDBETWEEN(30,500) -> 79 | G15: =RANDBETWEEN(30,500) -> 351 | H15: =RANDBETWEEN(30,500) -> 328 | J15: 116 | K15: 196 | L15: 91 | M15: 266 | N15: 257 | O15: 217 | R15: find and replace = ctrl + f
C16: =RANDBETWEEN(30,500) -> 47 | D16: =RANDBETWEEN(30,500) -> 32 | E16: =RANDBETWEEN(30,500) -> 302 | F16: =RANDBETWEEN(30,500) -> 264 | G16: =RANDBETWEEN(30,500) -> 97 | H16: =RANDBETWEEN(30,500) -> 77 | J16: 120 | K16: 275 | L16: 150 | M16: 377 | N16: 349 | O16: 370 | R16: find and replace have some limitations
C17: =RANDBETWEEN(30,500) -> 201 | D17: =RANDBETWEEN(30,500) -> 116 | E17: =RANDBETWEEN(30,500) -> 380 | F17: =RANDBETWEEN(30,500) -> 480 | G17: =RANDBETWEEN(30,500) -> 329 | H17: =RANDBETWEEN(30,500) -> 390 | J17: 233 | K17: 350 | L17: 357 | M17: 292 | N17: 265 | O17: 123 | R17: we have give particular rule in format we get right things
C18: =RANDBETWEEN(30,500) -> 493 | D18: =RANDBETWEEN(30,500) -> 32 | E18: =RANDBETWEEN(30,500) -> 467 | F18: =RANDBETWEEN(30,500) -> 210 | G18: =RANDBETWEEN(30,500) -> 122 | H18: =RANDBETWEEN(30,500) -> 127 | J18: 47 | K18: 217 | L18: 448 | M18: 184 | N18: 99 | O18: 498
R19: transpose fn
R20: we used paste special to transpose required data
H22: find and replace example | R22: Flash fill
R23: Shortcut = Ctrl+E
G24: 249 | H24: 171 | I24: 458 | J24: 150 | K24: 303 | L24: 308
G25: 282 | H25: 280 | I25: 80 | J25: 259 | K25: 68 | L25: 271 | R25: HIDE SHORTCUTS
G26: 339 | H26: 171 | I26: 51 | J26: 380 | K26: 122 | L26: 494 | R26: Row = Ctrl+9
G27: 307 | H27: 76 | I27: 144 | J27: 44 | K27: 440 | L27: 429 | R27: Columns = Ctrl+0
G28: 454 | H28: 47 | I28: 163 | J28: 82 | K28: 325 | L28: 96
G29: 228 | H29: 77 | I29: 398 | J29: 244 | K29: 123 | L29: 38
G30: 72 | H30: nil | I30: 238 | J30: 237 | K30: nil | L30: 334
G31: 116 | H31: 196 | I31: 91 | J31: 266 | K31: 257 | L31: 217
G32: 120 | H32: 275 | I32: 150 | J32: 377 | K32: 349 | L32: 370
G33: 233 | H33: nil | I33: 357 | J33: 292 | K33: nil | L33: 123
G34: 47 | H34: 217 | I34: 448 | J34: 184 | K34: 99 | L34: 498
H39: Transpose fn in paste special
D41: Raw data
B43: 249 | C43: 171 | D43: 458 | E43: 150 | F43: 303 | G43: 308
B44: 282 | C44: 280 | D44: 80 | E44: 259 | F44: 68 | G44: 271
B45: 339 | C45: 171 | D45: 51 | E45: 380 | F45: 122 | G45: 494
B46: 307 | C46: 76 | D46: 144 | E46: 44 | F46: 440 | G46: 429
B47: 454 | C47: 47 | D47: 163 | E47: 82 | F47: 325 | G47: 96
B48: 228 | C48: 77 | D48: 398 | E48: 244 | F48: 123 | G48: 38
B49: 72 | C49: nil | D49: 238 | E49: 237 | F49: nil | G49: 334
B50: 116 | C50: 196 | D50: 91 | E50: 266 | F50: 257 | G50: 217
B51: 120 | C51: 275 | D51: 150 | E51: 377 | F51: 349 | G51: 370
B52: 233 | C52: nil | D52: 357 | E52: 292 | F52: nil | G52: 123
B53: 47 | C53: 217 | D53: 448 | E53: 184 | F53: 99 | G53: 498
F56: Transpose Above Raw Data
B58: 249 | C58: 282 | D58: 339 | E58: 307 | F58: 454 | G58: 228 | H58: 72 | I58: 116 | J58: 120 | K58: 233 | L58: 47
B59: 171 | C59: 280 | D59: 171 | E59: 76 | F59: 47 | G59: 77 | H59: nil | I59: 196 | J59: 275 | K59: nil | L59: 217
B60: 458 | C60: 80 | D60: 51 | E60: 144 | F60: 163 | G60: 398 | H60: 238 | I60: 91 | J60: 150 | K60: 357 | L60: 448
B61: 150 | C61: 259 | D61: 380 | E61: 44 | F61: 82 | G61: 244 | H61: 237 | I61: 266 | J61: 377 | K61: 292 | L61: 184
B62: 303 | C62: 68 | D62: 122 | E62: 440 | F62: 325 | G62: 123 | H62: nil | I62: 257 | J62: 349 | K62: nil | L62: 99
B63: 308 | C63: 271 | D63: 494 | E63: 429 | F63: 96 | G63: 38 | H63: 334 | I63: 217 | J63: 370 | K63: 123 | L63: 498

Sheet REFERENCE
C2: 3 MODULE
D4: RELATIVE REFERENCE
C7: Product | D7: Category | E7: Department | F7: Purchase Price | G7: Sale Price | H7: Profit/Loss
C8: Dry Tissues | D8: Cleaning Supplies | E8: Household | F8: 120 | G8: 135 | H8: =G8-F8 -> 15 | J8: =_xlfn.FORMULATEXT(H8) -> =G8-F8
C9: Paper Towels | D9: Cleaning Supplies | E9: Household | F9: 125 | G9: 135 | H9: =G9-F9 -> 10
C10: Wet Wipes | D10: Cleaning Supplies | E10: Household | F10: 120 | G10: 135 | H10: =G10-F10 -> 15
C11: Chicken Dinner | D11: Frozen Foods | E11: Grocery | F11: 80 | G11: 155 | H11: =G11-F11 -> 75
C12: Clear Refresher | D12: Soft Drinks | E12: Grocery | F12: 165 | G12: 100 | H12: =G12-F12 -> -65
C13: Dried Grits | D13: Salty Snacks | E13: Grocery | F13: 180 | G13: 100 | H13: =G13-F13 -> -80
C14: Extra Nougat | D14: Candy | E14: Grocery | F14: 145 | G14: 115 | H14: =G14-F14 -> -30
C15: Athletic Drink | D15: Soft Drinks | E15: Grocery | F15: 75 | G15: 155 | H15: =G15-F15 -> 80
C16: Stew | D16: Frozen Foods | E16: Grocery | F16: 80 | G16: 155 | H16: =G16-F16 -> 75
C17: Jerky | D17: Salty Snacks | E17: Grocery | F17: 160 | G17: 100 | H17: =G17-F17 -> -60
C18: Dry Tissues | D18: Cleaning Supplies | E18: Household | F18: 168 | G18: 100 | H18: =G18-F18 -> -68
C19: Paper Towels | D19: Cleaning Supplies | E19: Household | F19: 90 | G19: 155 | H19: =G19-F19 -> 65
C20: Wet Wipes | D20: Cleaning Supplies | E20: Household | F20: 120 | G20: 135 | H20: =G20-F20 -> 15
... C107: Jerky | D107: Salty Snacks | E107: Grocery | F107: 160 | G107: 100 | H107: =G107-F107 -> -60
F110: ABSOLUTE REFERENCE
C112: In these we fixed a cell value using dollar sign as shown in right side
K113: 0.12
C114: Date | D114: Order Number | E114: Customer | F114: Quantity | G114: Category | H114: Code | I114: Unit Price | J114: Gross Sales | K114: GST | L114: Amount
C115: 43072 | D115: 1 | E115: Hindol Sinha | F115: 5 | G115: Suits | H115: W1 | I115: 3200 | J115: 16000 | K115: =J115*$K$113 -> 1920 | L115: 16800 | N115: =_xlfn.FORMULATEXT(K115) -> =J115*$K$113
C116: 43074 | D116: 2 | E116: Dola Das | F116: 3 | G116: Coats | H116: H2 | I116: 1250 | J116: 3750 | K116: =J116*$K$113 -> 450 | L116: 3937.5
C117: 43079 | D117: 3 | E117: Deepak Sharma | F117: 4 | G117: Coats | H117: C4 | I117: 1250 | J117: 5000 | K117: =J117*$K$113 -> 600 | L117: 5250
C118: 43081 | D118: 4 | E118: Uma Nag | F118: 12 | G118: Ties | H118: T1 | I118: 150 | J118: 1800 | K118: =J118*$K$113 -> 216 | L118: 1890
C119: 43084 | D119: 5 | E119: Sayak Pal | F119: 6 | G119: Hats | H119: C1 | I119: 99 | J119: 594 | K119: =J119*$K$113 -> 71.28 | L119: 623.7
C120: 43089 | D120: 6 | E120: Srijan Das | F120: 10 | G120: Suits | H120: W1 | I120: 3200 | J120: 32000 | K120: =J120*$K$113 -> 3840 | L120: 33600
C121: 43090 | D121: 7 | E121: Srijita Agarwal | F121: 5 | G121: Shoes | H121: H1 | I121: 590 | J121: 2950 | K121: =J121*$K$113 -> 354 | L121: 3097.5
C122: 43092 | D122: 8 | E122: Rina Karmakar | F122: 2 | G122: Hats | H122: S2 | I122: 99 | J122: 198 | K122: =J122*$K$113 -> 23.76 | L122: 207.9
C123: 43095 | D123: 9 | E123: Lily Roy | F123: 10 | G123: Ties | H123: T5 | I123: 150 | J123: 1500 | K123: =J123*$K$113 -> 180 | L123: 1575
C124: 43099 | D124: 10 | E124: Sonali Gupta | F124: 5 | G124: Shoes | H124: S2 | I124: 590 | J124: 2950 | K124: =J124*$K$113 -> 354 | L124: 3097.5
C125: 43072 | D125: 11 | E125: Deepali Srivastava | F125: 3 | G125: Suits | H125: W1 | I125: 3200 | J125: 9600 | K125: =J125*$K$113 -> 1152 | L125: 10080
C126: 43074 | D126: 12 | E126: Rakhi | F126: 3 | G126: Coats | H126: H2 | I126: 1250 | J126: 3750 | K126: =J126*$K$113 -> 450 | L126: 3937.5
C127: 43079 | D127: 13 | E127: Deepak Chandra Fulara | F127: 4 | G127: Coats | H127: C4 | I127: 1250 | J127: 5000 | K127: =J127*$K$113 -> 600 | L127: 5250
... C194: 43099 | D194: 80 | E194: Deblina Ghatak | F194: 5 | G194: Shoes | H194: S2 | I194: 590 | J194: 2950 | K194: =J194*$K$113 -> 354 | L194: 3097.5
D197: MIXED REFERENCE
C199: In these we fixed a single row cell number using dollar sign as shown in right side for calculation
C202: Sales Person | D202: Target (in INR) | E202: 0.12 | F202: 0.08 | G202: 0.15 | H202: 0.25 | I202: 0.22 | J202: 0.18
E203: January | F203: February | G203: March | H203: April | I203: May | J203: June
C204: Jinia Ghosh | D204: 164506 | E204: =D204*E$202 -> 19740.72 | F204: =E204*F$202 -> 1579.2576 | G204: =F204*G$202 -> 236.88864 | H204: =G204*H$202 -> 59.22216 | I204: =H204*I$202 -> 13.028875 | J204: =I204*J$202 -> 2.3451975 | N204: =_xlfn.FORMULATEXT(E204) -> =D204*E$202
C205: Alok Kundu | D205: 186343 | E205: =D205*E$202 -> 22361.16 | F205: =E205*F$202 -> 1788.8928 | G205: =F205*G$202 -> 268.33392 | H205: =G205*H$202 -> 67.08348 | I205: =H205*I$202 -> 14.758366 | J205: =I205*J$202 -> 2.6565058
C206: Soham Das | D206: 155543 | E206: =D206*E$202 -> 18665.16 | F206: =E206*F$202 -> 1493.2128 | G206: =F206*G$202 -> 223.98192 | H206: =G206*H$202 -> 55.99548 | I206: =H206*I$202 -> 12.319006 | J206: =I206*J$202 -> 2.217421
C207: Sandip Jana | D207: 101719 | E207: =D207*E$202 -> 12206.28 | F207: =E207*F$202 -> 976.5024 | G207: =F207*G$202 -> 146.47536 | H207: =G207*H$202 -> 36.61884 | I207: =H207*I$202 -> 8.0561448 | J207: =I207*J$202 -> 1.4501061
C208: Nilay Guha | D208: 192612 | E208: =D208*E$202 -> 23113.44 | F208: =E208*F$202 -> 1849.0752 | G208: =F208*G$202 -> 277.36128 | H208: =G208*H$202 -> 69.34032 | I208: =H208*I$202 -> 15.25487 | J208: =I208*J$202 -> 2.7458767
C209: Mrinal Kayal | D209: 198205 | E209: =D209*E$202 -> 23784.6 | F209: =E209*F$202 -> 1902.768 | G209: =F209*G$202 -> 285.4152 | H209: =G209*H$202 -> 71.3538 | I209: =H209*I$202 -> 15.697836 | J209: =I209*J$202 -> 2.8256105
C210: Keya Barman | D210: 160259 | E210: =D210*E$202 -> 19231.08 | F210: =E210*F$202 -> 1538.4864 | G210: =F210*G$202 -> 230.77296 | H210: =G210*H$202 -> 57.69324 | I210: =H210*I$202 -> 12.692513 | J210: =I210*J$202 -> 2.2846523
C211: Joy Saha | D211: 102034 | E211: =D211*E$202 -> 12244.08 | F211: =E211*F$202 -> 979.5264 | G211: =F211*G$202 -> 146.92896 | H211: =G211*H$202 -> 36.73224 | I211: =H211*I$202 -> 8.0810928 | J211: =I211*J$202 -> 1.4545967
C212: Mithun Chaudhury | D212: 167168 | E212: =D212*E$202 -> 20060.16 | F212: =E212*F$202 -> 1604.8128 | G212: =F212*G$202 -> 240.72192 | H212: =G212*H$202 -> 60.18048 | I212: =H212*I$202 -> 13.239706 | J212: =I212*J$202 -> 2.383147
C213: Manas Das | D213: 136425 | E213: =D213*E$202 -> 16371 | F213: =E213*F$202 -> 1309.68 | G213: =F213*G$202 -> 196.452 | H213: =G213*H$202 -> 49.113 | I213: =H213*I$202 -> 10.80486 | J213: =I213*J$202 -> 1.9448748
C214: Jinia Ghosh | D214: 105123 | E214: =D214*E$202 -> 12614.76 | F214: =E214*F$202 -> 1009.1808 | G214: =F214*G$202 -> 151.37712 | H214: =G214*H$202 -> 37.84428 | I214: =H214*I$202 -> 8.3257416 | J214: =I214*J$202 -> 1.4986335
C215: Alok Kundu | D215: 103627 | E215: =D215*E$202 -> 12435.24 | F215: =E215*F$202 -> 994.8192 | G215: =F215*G$202 -> 149.22288 | H215: =G215*H$202 -> 37.30572 | I215: =H215*I$202 -> 8.2072584 | J215: =I215*J$202 -> 1.4773065
C216: Soham Das | D216: 135386 | E216: =D216*E$202 -> 16246.32 | F216: =E216*F$202 -> 1299.7056 | G216: =F216*G$202 -> 194.95584 | H216: =G216*H$202 -> 48.73896 | I216: =H216*I$202 -> 10.722571 | J216: =I216*J$202 -> 1.9300628
... C297: Sandip Jana | D297: 146233 | E297: =D297*E$202 -> 17547.96 | F297: =E297*F$202 -> 1403.8368 | G297: =F297*G$202 -> 210.57552 | H297: =G297*H$202 -> 52.64388 | I297: =H297*I$202 -> 11.581654 | J297: =I297*J$202 -> 2.0846976

Sheet DATA ARRANGEMENT
E2: 4 MODULE
E4: DATA ARRANGEMENT | N4: POINTS TO BE NOTED
F6: text to column
N8: Rib (data) = txt to column
B9: Names | D9: first Name | E9: last name
B10: Rahul Sharma | D10: Rahul | E10: Sharma | N10: separate name in first and last using this fn
B11: Priya Patel | D11: Priya | E11: Patel | N11: we can do more things separate as per need
B12: Amit Singh | D12: Amit | E12: Singh
B13: Anjali Gupta | D13: Anjali | E13: Gupta | N13: Rib (data) = remove duplication fn
B14: Suresh Kumar | D14: Suresh | E14: Kumar | N14: remove same data from workbook/sheet( selected cells only)
B15: Pooja Reddy | D15: Pooja | E15: Reddy
B16: Vikram Malhotra | D16: Vikram | E16: Malhotra | N16: Rib (data) = Data validation
B17: Aarti Desai | D17: Aarti | E17: Desai | N17: validation means giving certain rules
B18: Arjun Choudhury | D18: Arjun | E18: Choudhury | N18: if not performed correctly it shows error
B19: Naina Iyer | D19: Naina | E19: Iyer | N19: formula for only txt and symbol =istext(A1:Z1)
B20: Rajesh Verma | D20: Rajesh | E20: Verma | N20: formula for only numbers =isnumber(A1:Z1)
B21: Kavita Mishra | D21: Kavita | E21: Mishra
B22: Aditya Joshi | D22: Aditya | E22: Joshi | N22: Data Protection
B23: Deepika Khanna | D23: Deepika | E23: Khanna | N23: Rib(review) = protect sheet
B24: Ravi Menon | D24: Ravi | E24: Menon | N24: if help to protect data from changes by any person
B25: Sneha Shah | D25: Sneha | E25: Shah
B26: Mohan Rao | D26: Mohan | E26: Rao
B27: Jaya Mehta | D27: Jaya | E27: Mehta
B28: Karthik Nair | D28: Karthik | E28: Nair
B29: Geeta Bhat | D29: Geeta | E29: Bhat
E33: Remove duplicate data
B35: RAW DATA | D35: using duplicate fn
B37: Names | D37: Names
B38: Rahul Sharma | D38: Rahul Sharma
B39: Priya Patel | D39: Priya Patel
B40: Amit Singh | D40: Amit Singh
B41: Anjali Gupta | D41: Anjali Gupta
B42: Suresh Kumar | D42: Suresh Kumar
B43: Pooja Reddy | D43: Pooja Reddy
B44: Vikram Malhotra | D44: Vikram Malhotra
B45: Aarti Desai | D45: Aarti Desai
B46: Arjun Choudhury | D46: Arjun Choudhury
B47: Naina Iyer | D47: Naina Iyer
... B57: Geeta Bhat | D57: Geeta Bhat
B58: Deepika Khanna
B59: Ravi Menon
B60: Sneha Shah
B61: Mohan Rao
B62: Jaya Mehta
B63: Karthik Nair
B64: Geeta Bhat
D68: Data Validation
B70: Raw Data | D70: Data validation | F70: Raw Data | H70: Data validation
B71: Names | D71: Names | F71: 150 | H71: 150
B72: Rahul Sharma | D72: Rahul Sharma | F72: 259 | H72: 259
B73: Priya Patel | D73: Priya Patel | F73: 380 | H73: 380
B74: Amit Singh | D74: Amit Singh | F74: 44 | H74: 44
B75: Anjali Gupta | D75: Anjali Gupta | F75: 82 | H75: 82
B76: Suresh Kumar | D76: Suresh Kumar | F76: 244
B77: Pooja Reddy | D77: Pooja Reddy | F77: 237 | H77: 237
B78: Vikram Malhotra | D78: Vikram Malhotra | F78: 266 | H78: 266
B79: Aarti Desai | D79: Aarti Desai | F79: 377 | H79: 377
B80: Arjun Choudhury | D80: Arjun Choudhury | F80: 292
B81: Naina Iyer | D81: Naina Iyer | F81: 184 | H81: 184
B82: Rajesh Verma | F82: 458 | H82: 458
B83: Kavita Mishra | D83: Kavita Mishra | F83: 80 | H83: 80
B84: Aditya Joshi | D84: Aditya Joshi | F84: 51 | H84: 51
B85: Deepika Khanna | F85: 144
B86: Ravi Menon | D86: Ravi Menon | F86: 163 | H86: 163
B87: Sneha Shah | D87: Sneha Shah | F87: 398 | H87: 398
B88: Mohan Rao | D88: Mohan Rao | F88: 238
B89: Jaya Mehta | F89: 91 | H89: 91
B90: Karthik Nair | D90: Karthik Nair | F90: 150 | H90: 150
B91: Geeta Bhat | D91: Geeta Bhat | F91: 357 | H91: 357

Sheet SUBTOTAL
B3: 5 MODULE
B5: Subtotal , Group and Ungroup | J5: POINTS TO BE NOTED
D7: Sale data of jacket by A Limited company
C9: City | D9: Item Number | E9: Quantity | F9: Price (per product, ₹) | G9: Amount (₹)
C10: Mumbai | D10: 1 | E10: 50 | F10: 1500 | G10: 75000
C11: Delhi | D11: 2 | E11: 45 | F11: 1600 | G11: 72000
C12: Bangalore | D12: 3 | E12: 55 | F12: 1450 | G12: 79750
C13: Kolkata | D13: 4 | E13: 40 | F13: 1700 | G13: 68000
C14: Chennai | D14: 5 | E14: 60 | F14: 1400 | G14: 84000
C15: Hyderabad | D15: 6 | E15: 35 | F15: 1550 | G15: 54250
C16: Ahmedabad | D16: 7 | E16: 42 | F16: 1480 | G16: 62160
C17: Pune | D17: 8 | E17: 48 | F17: 1530 | G17: 73440
C18: Jaipur | D18: 9 | E18: 38 | F18: 1680 | G18: 63840
C19: Lucknow | D19: 10 | E19: 30 | F19: 1600 | G19: 48000
C20: Chandigarh | D20: 11 | E20: 32 | F20: 1550 | G20: 49600
C21: Indore | D21: 12 | E21: 25 | F21: 1700 | G21: 42500
... C59: Chennai | D59: 50 | E59: 35 | F59: 1410 | G59: 49350
E61: Arranging the Data
C63: City | D63: Item Number | E63: Quantity | F63: Price (per product, ₹) | G63: Amount (₹)
C64: Ahmedabad | D64: 7 | E64: 42 | F64: 1480 | G64: 62160
C65: Ahmedabad | D65: 22 | E65: 42 | F65: 1490 | G65: 62580
C66: Ahmedabad | D66: 37 | E66: 40 | F66: 1500 | G66: 60000
C67: Ahmedabad Total | G67: =SUBTOTAL(9,G64:G66) -> 184740
C68: Bangalore | D68: 3 | E68: 55 | F68: 1450 | G68: 79750
C69: Bangalore | D69: 18 | E69: 50 | F69: 1480 | G69: 74000
C70: Bangalore | D70: 33 | E70: 58 | F70: 1470 | G70: 85460
C71: Bangalore | D71: 48 | E71: 45 | F71: 1490 | G71: 67050
C72: Bangalore Total | G72: =SUBTOTAL(9,G68:G71) -> 306260
C73: Chandigarh | D73: 11 | E73: 32 | F73: 1550 | G73: 49600
C74: Chandigarh | D74: 26 | E74: 30 | F74: 1560 | G74: 46800
C75: Chandigarh | D75: 41 | E75: 22 | F75: 1570 | G75: 34540
C76: Chandigarh Total | G76: =SUBTOTAL(9,G73:G75) -> 130940
C77: Chennai | D77: 5 | E77: 60 | F77: 1400 | G77: 84000
C78: Chennai | D78: 20 | E78: 52 | F78: 1420 | G78: 73840
C79: Chennai | D79: 35 | E79: 50 | F79: 1430 | G79: 71500
C80: Chennai | D80: 50 | E80: 35 | F80: 1410 | G80: 49350
C81: Chennai Total | G81: =SUBTOTAL(9,G77:G80) -> 278690
C82: Delhi | D82: 2 | E82: 45 | F82: 1600 | G82: 72000
C83: Delhi | D83: 17 | E83: 60 | F83: 1580 | G83: 94800
C84: Delhi | D84: 32 | E84: 55 | F84: 1590 | G84: 87450
C85: Delhi | D85: 47 | E85: 52 | F85: 1570 | G85: 81640
C86: Delhi Total | G86: =SUBTOTAL(9,G82:G85) -> 335890
C87: Hyderabad | D87: 6 | E87: 35 | F87: 1550 | G87: 54250
C88: Hyderabad | D88: 21 | E88: 48 | F88: 1540 | G88: 73920
C89: Hyderabad | D89: 36 | E89: 38 | F89: 1560 | G89: 59280
C90: Hyderabad Total | G90: =SUBTOTAL(9,G87:G89) -> 187450
C91: Indore | D91: 12 | E91: 25 | F91: 1700 | G91: 42500
C92: Indore | D92: 27 | E92: 35 | F92: 1720 | G92: 60200
C93: Indore | D93: 42 | E93: 20 | F93: 1730 | G93: 34600
C94: Indore Total | G94: =SUBTOTAL(9,G91:G93) -> 137300
C95: Jaipur | D95: 9 | E95: 38 | F95: 1680 | G95: 63840
C96: Jaipur | D96: 24 | E96: 43 | F96: 1670 | G96: 71910
C97: Jaipur | D97: 39 | E97: 32 | F97: 1690 | G97: 54080
C98: Jaipur Total | G98: =SUBTOTAL(9,G95:G97) -> 189830
C99: Kolkata | D99: 4 | E99: 40 | F99: 1700 | G99: 68000
C100: Kolkata | D100: 19 | E100: 45 | F100: 1690 | G100: 76050
C101: Kolkata | D101: 34 | E101: 42 | F101: 1680 | G101: 70560
C102: Kolkata | D102: 49 | E102: 40 | F102: 1690 | G102: 67600
C103: Kolkata Total | G103: =SUBTOTAL(9,G99:G102) -> 282210
C104: Lucknow | D104: 10 | E104: 30 | F104: 1600 | G104: 48000
C105: Lucknow | D105: 25 | E105: 28 | F105: 1590 | G105: 44520
C106: Lucknow | D106: 40 | E106: 25 | F106: 1610 | G106: 40250
C107: Lucknow Total | G107: =SUBTOTAL(9,G104:G106) -> 132770
C108: Mumbai | D108: 1 | E108: 50 | F108: 1500 | G108: 75000
C109: Mumbai | D109: 16 | E109: 55 | F109: 1520 | G109: 83600
C110: Mumbai | D110: 31 | E110: 60 | F110: 1540 | G110: 92400
C111: Mumbai | D111: 46 | E111: 58 | F111: 1530 | G111: 88740
C112: Mumbai Total | G112: =SUBTOTAL(9,G108:G111) -> 339740
C113: Nagpur | D113: 15 | E113: 20 | F113: 1500 | G113: 30000
C114: Nagpur | D114: 30 | E114: 18 | F114: 1510 | G114: 27180
C115: Nagpur | D115: 45 | E115: 12 | F115: 1520 | G115: 18240
C116: Nagpur Total | G116: =SUBTOTAL(9,G113:G115) -> 75420
C117: Pune | D117: 8 | E117: 48 | F117: 1530 | G117: 73440
C118: Pune | D118: 23 | E118: 37 | F118: 1510 | G118: 55870
C119: Pune | D119: 38 | E119: 45 | F119: 1520 | G119: 68400
C120: Pune Total | G120: =SUBTOTAL(9,G117:G119) -> 197710
C121: Surat | D121: 13 | E121: 27 | F121: 1450 | G121: 39150
C122: Surat | D122: 28 | E122: 32 | F122: 1460 | G122: 46720
C123: Surat | D123: 43 | E123: 18 | F123: 1480 | G123: 26640
C124: Surat Total | G124: =SUBTOTAL(9,G121:G123) -> 112510
C125: Visakhapatnam | D125: 14 | E125: 22 | F125: 1800 | G125: 39600
C126: Visakhapatnam | D126: 29 | E126: 24 | F126: 1780 | G126: 42720
C127: Visakhapatnam | D127: 44 | E127: 15 | F127: 1810 | G127: 27150
C128: Visakhapatnam Total | G128: =SUBTOTAL(9,G125:G127) -> 109470
C129: Grand Total | G129: =SUBTOTAL(9,G64:G127) -> 3000930

Sheet CONDITIONAL FORMATTING
D2: 6 MODULE
D4: Conditional formatting | P4: POINTS TO BE NOTED
B6: QUESTION
B7: You have a spreadsheet with sales data for the first 10 months of a year. The data is in a table format with the months in column Months and the sales figures in column Sale
B8: You want to apply conditional formatting to the sales figures to highlight the following: | P8: can use multiple conditional on particular data
P9: to make a filter that only this text or nujmber should be contain we can use data validation
B10: 1. Sales figures greater than 10,000 should be highlighted in green. | P10: we used reference in workbook Q8
B11: 2. Sales figures between 5,000 and 10,000 should be highlighted in yellow.
B12: 3. Sales figures less than 5,000 should be highlighted in red.
D14: Conditional formating
C16: Month | D16: shoes name | E16: Qt | F16: Sale [INR] | H16: Month | I16: shoes name | J16: Qt | K16: Sale [INR]
C17: Jan | D17: Nike | E17: 150 | F17: 35000 | H17: Jan | I17: Nike | J17: 150 | K17: 35000
C18: Jan | D18: Adidas | E18: 120 | F18: 25000 | H18: Jan | I18: Adidas | J18: 120 | K18: 25000
C19: Jan | D19: Puma | E19: 80 | F19: 12000 | H19: Jan | I19: Puma | J19: 80 | K19: 12000
C20: Jan | D20: Reebok | E20: 100 | F20: 20000 | H20: Jan | I20: Reebok | J20: 100 | K20: 7880
C21: Jan | D21: Asics | E21: 140 | F21: 32000 | H21: Jan | I21: Asics | J21: 140 | K21: 32000
C22: Jan | D22: Skechers | E22: 110 | F22: 18000 | H22: Jan | I22: Skechers | J22: 110 | K22: 18000
C23: Jan | D23: New Balance | E23: 70 | F23: 10000 | H23: Jan | I23: New Balance | J23: 70 | K23: 10000
C24: Jan | D24: Under Armour | E24: 90 | F24: 15500 | H24: Jan | I24: Under Armour | J24: 90 | K24: 15500
C25: Jan | D25: Converse | E25: 130 | F25: 28000 | H25: Jan | I25: Converse | J25: 130 | K25: 28000
C26: Jan | D26: Vans | E26: 60 | F26: 8000 | H26: Jan | I26: Vans | J26: 60 | K26: 8000
C27: Feb | D27: Nike | E27: 160 | F27: 38000 | H27: Feb | I27: Nike | J27: 160 | K27: 38000
C28: Feb | D28: Adidas | E28: 130 | F28: 26000 | H28: Feb | I28: Adidas | J28: 130 | K28: 26000
... C66: May | D66: Vans | E66: 80 | F66: 12000 | H66: May | I66: Vans | J66: 80 | K66: 12000
C69: workbook Q1
C71: Date | D71: Product | E71: Region | F71: Amount | H71: change in product | I71: Dairy
C72: 43930 | D72: Dairy | E72: Denmark | F72: 1148 | H72: change in Amount | I72: 300
C73: 43977 | D73: Produce | E73: Denmark | F73: 1530
C74: 43806 | D74: Produce | E74: Denmark | F74: 1423.5
E75: Denmark Total | F75: =SUBTOTAL(9,F72:F74) -> 4101.5
C76: 43774 | D76: Dairy | E76: Finland | F76: 192.1
C77: 44024 | D77: Dairy | E77: Finland | F77: 351
C78: 43984 | D78: Grain | E78: Finland | F78: 560.4
E79: Finland Total | F79: =SUBTOTAL(9,F76:F78) -> 1103.5
C80: 44073 | D80: Dairy | E80: Germany | F80: 470
C81: 44038 | D81: Dairy | E81: Germany | F81: 17.4
C82: 44098 | D82: Grain | E82: Germany | F82: 1405
C83: 44134 | D83: Grain | E83: Germany | F83: 470
C84: 44069 | D84: Grain | E84: Germany | F84: 17.4
C85: 44019 | D85: Grain | E85: Germany | F85: 747
C86: 44008 | D86: Produce | E86: Germany | F86: 17.4
C87: 44019 | D87: Produce | E87: Germany | F87: 747
E88: Germany Total | F88: =SUBTOTAL(9,F80:F87) -> 3891.2
C89: 43848 | D89: Dairy | E89: Italy | F89: 3194.2
C90: 43874 | D90: Dairy | E90: Italy | F90: 438.43
C91: 43817 | D91: Produce | E91: Italy | F91: 3194.2
C92: 43903 | D92: Produce | E92: Italy | F92: 438.43
C95: workbook Q2
E97: above 20 | F97: average | G97: bottom 10
C98: City | D98: Date | E98: Fee | F98: Attendance | G98: Books Sold
C99: Anchorage | D99: 43905 | E99: 1038 | F99: 179 | G99: 98
C100: Atlanta | D100: 43869 | E100: 1880 | F100: 149 | G100: 95
C101: Boston | D101: 43855 | E101: 821 | F101: 385 | G101: 146
C102: Charleston | D102: 43859 | E102: 1822 | F102: 328 | G102: 124
C103: Cleveland | D103: 43871 | E103: 1073 | F103: 128 | G103: 32
C104: Detroit | D104: 43875 | E104: 1881 | F104: 376 | G104: 58
C105: Flagstaff | D105: 43915 | E105: 1222 | F105: 37 | G105: 5
C106: Los Angeles | D106: 43895 | E106: 945 | F106: 265 | G106: 47
C107: Memphis | D107: 43867 | E107: 910 | F107: 93 | G107: 45
C108: New Orleans | D108: 43921 | E108: 1233 | F108: 415 | G108: 59
C109: New York | D109: 43853 | E109: 1180 | F109: 205 | G109: 147
C110: Philadelphia | D110: 43861 | E110: 1965 | F110: 145 | G110: 31
... C120: Washington, D.C. | D120: 43857 | E120: 1724 | F120: 499 | G120: 151
C123: workbook Q3
C125: Student | D125: Quiz1 | E125: Exam1 | F125: Quiz2 | G125: Exam2 | H125: Grade
C126: Nancy | D126: 96 | E126: 97 | F126: 90 | G126: 82 | H126: =(D126+(E126*3)+F126+(G126*3))/8 -> 90.375
C127: Andrew | D127: 59 | E127: 55 | F127: 71 | G127: 94 | H127: =(D127+(E127*3)+F127+(G127*3))/8 -> 72.125
C128: Janet | D128: 69 | E128: 71 | F128: 98 | G128: 98 | H128: =(D128+(E128*3)+F128+(G128*3))/8 -> 84.25
C129: Margaret | D129: 99 | E129: 90 | F129: 59 | G129: 79 | H129: =(D129+(E129*3)+F129+(G129*3))/8 -> 83.125
C130: Steven | D130: 56 | E130: 86 | F130: 65 | G130: 74 | H130: =(D130+(E130*3)+F130+(G130*3))/8 -> 75.125
C131: Michael | D131: 57 | E131: 61 | F131: 84 | G131: 67 | H131: =(D131+(E131*3)+F131+(G131*3))/8 -> 65.625
C132: Robert | D132: 55 | E132: 86 | F132: 59 | G132: 86 | H132: =(D132+(E132*3)+F132+(G132*3))/8 -> 78.75
C133: Laura | D133: 89 | E133: 91 | F133: 91 | G133: 81 | H133: =(D133+(E133*3)+F133+(G133*3))/8 -> 87
C134: Anne | D134: 55 | E134: 77 | F134: 91 | G134: 86 | H134: =(D134+(E134*3)+F134+(G134*3))/8 -> 79.375
C137: workbook Q4
D139: 5 | E139: 4 | F139: 3 | G139: 2 | H139: 1
C140: Product | D140: Shifting | E140: Brakes | F140: Handle Bars | G140: Seat | H140: Frequency of Repair | I140: Overall Score
C141: Mountain Bike | D141: 5 | E141: 1 | F141: 1 | G141: 2 | H141: 3 | I141: =AVERAGE(D141:H141) -> 2.4
C142: Comfort Rider | D142: 4 | E142: 3 | F142: 3 | G142: 5 | H142: 4 | I142: =AVERAGE(D142:H142) -> 3.8
C143: Hybrid | D143: 3 | E143: 3 | F143: 3 | G143: 3 | H143: 2 | I143: =AVERAGE(D143:H143) -> 2.8
C144: Road Bike | D144: 3 | E144: 1 | F144: 1 | G144: 2 | H144: 1 | I144: =AVERAGE(D144:H144) -> 1.6
C145: Recumbant | D145: 2 | E145: 3 | F145: 3 | G145: 4 | H145: 2 | I145: =AVERAGE(D145:H145) -> 2.8
C146: Unicycle | D146: 3 | E146: 2 | F146: 2 | G146: 1 | H146: 5 | I146: =AVERAGE(D146:H146) -> 2.6
C149: workbook Q5
C151: FY 2020 | D151: Profits | E151: Trend
C152: July | D152: 5000
C153: August | D153: 7000 | E153: =D153-D152 -> 2000
C154: September | D154: 10000 | E154: =D154-D153 -> 3000
C155: October | D155: 2500 | E155: =D155-D154 -> -7500
C156: November | D156: 4000 | E156: =D156-D155 -> 1500
C157: December | D157: 9800 | E157: =D157-D156 -> 5800
C158: January | D158: 5400 | E158: =D158-D157 -> -4400
C159: February | D159: 6700 | E159: =D159-D158 -> 1300
C160: March | D160: 4300 | E160: =D160-D159 -> -2400
C161: April | D161: 11000 | E161: =D161-D160 -> 6700
C162: May | D162: 12500 | E162: =D162-D161 -> 1500
C163: June | D163: 9800 | E163: =D163-D162 -> -2700
C166: workbook Q6
D168: < $900,000
C169: Region | D169: Sales
...

Sheet ANALYSIS
C2: 7 MODULE
C4: What if Analysis fn | K4: POINTS TO BE NOTED
B7: Question: | K7: data(what if analysis)
K8: to convert in 50 to 5,00,000 ( multiple formula with desire zeroes )
B9: You are managing a car showroom and have data about the cost, selling price, and units sold for different car brands over the past five months. | K9: for comma = used number format (use separator)
B10: You want to analyze how changes in costs and selling prices affect your total profit. The data is organized as follows:
K11: Face value formula
K12: FV(percentage/12, years*12, - monthly inv, - intial inv)
B13: Month | C13: Car Brand | D13: Cost (₹ Lakhs) | E13: Selling Price (₹ Lakhs) | F13: Units Sold | G13: Total Profit (₹ Lakhs)
B14: Jan | C14: Toyota | D14: 15 | E14: 20 | F14: 10 | G14: =E14*F14-D14*F14 -> 50
B15: Jan | C15: Honda | D15: 12 | E15: 18 | F15: 8 | G15: =E15*F15-D15*F15 -> 48
B16: Jan | C16: Ford | D16: 14 | E16: 19 | F16: 7 | G16: =E16*F16-D16*F16 -> 35
B17: Jan | C17: BMW | D17: 25 | E17: 35 | F17: 5 | G17: =E17*F17-D17*F17 -> 50
B18: Jan | C18: Audi | D18: 30 | E18: 45 | F18: 4 | G18: =E18*F18-D18*F18 -> 60
B19: Feb | C19: Toyota | D19: 15 | E19: 21 | F19: 12 | G19: =E19*F19-D19*F19 -> 72
B20: Feb | C20: Honda | D20: 12 | E20: 19 | F20: 9 | G20: =E20*F20-D20*F20 -> 63
B21: Feb | C21: Ford | D21: 14 | E21: 20 | F21: 6 | G21: =E21*F21-D21*F21 -> 36
B22: Feb | C22: BMW | D22: 25 | E22: 36 | F22: 6 | G22: =E22*F22-D22*F22 -> 66
B23: Feb | C23: Audi | D23: 30 | E23: 46 | F23: 5 | G23: =E23*F23-D23*F23 -> 80
B24: Mar | C24: Toyota | D24: 16 | E24: 22 | F24: 11 | G24: =E24*F24-D24*F24 -> 66
B25: Mar | C25: Honda | D25: 13 | E25: 20 | F25: 10 | G25: =E25*F25-D25*F25 -> 70
... B38: May | C38: Audi | D38: 33 | E38: 49 | F38: 8 | G38: =E38*F38-D38*F38 -> 128
B40: Tasks:
B42: 1. Calculate Total Profit: Use the formula for each row to calculate the total profit for each car brand in each month.
B44: 2. Scenario Analysis: Perform a scenario analysis to see how changes in the selling price of Toyota cars affect the total profit in the month of January. Assume three scenarios:
B45: Best case: Selling price increases by 10%.
B46: Most likely case: Selling price remains the same.
B47: Worst case: Selling price decreases by 10%.
B49: 3. Goal Seek Analysis: Use the Goal Seek tool to determine what the selling price of Audi cars should be in May to achieve a total profit of ₹200 lakhs for that month.
D52: Solving the Question
B53: Case 2
B54: Scenario | C54: Car Brand | D54: Cost (₹ Lakhs) | E54: Selling Price (₹ Lakhs) | F54: Units Sold | G54: Total Profit (₹ Lakhs)
B55: best case | C55: Toyota | D55: 15 | E55: 22 | F55: 10 | G55: =(E55*F55-D55*F55)*10000 -> 700000
B56: likely case | C56: Toyota | D56: 15 | E56: 20 | F56: 10 | G56: =(E56*F56-D56*F56)*10000 -> 500000
B57: worst case | C57: Toyota | D57: 15 | E57: 18 | F57: 10 | G57: =(E57*F57-D57*F57)*10000 -> 300000
B60: Case 3
B61: Month | C61: Car Brand | D61: Cost (₹ Lakhs) | E61: Selling Price (₹ Lakhs) | F61: Units Sold | G61: Total Profit (₹ Lakhs)
B62: Jan | C62: Toyota | D62: 15 | E62: 20 | F62: 10 | G62: =(E62*F62-D62*F62)*10000 -> 500000
B63: Jan | C63: Honda | D63: 12 | E63: 18 | F63: 8 | G63: =(E63*F63-D63*F63)*10000 -> 480000
B64: Jan | C64: Ford | D64: 14 | E64: 19 | F64: 7 | G64: =(E64*F64-D64*F64)*10000 -> 350000
B65: Jan | C65: BMW | D65: 25 | E65: 35 | F65: 5 | G65: =(E65*F65-D65*F65)*10000 -> 500000
B66: Jan | C66: Audi | D66: 30 | E66: 45 | F66: 4 | G66: =(E66*F66-D66*F66)*10000 -> 600000
B67: Feb | C67: Toyota | D67: 15 | E67: 21 | F67: 12 | G67: =(E67*F67-D67*F67)*10000 -> 720000
B68: Feb | C68: Honda | D68: 12 | E68: 19 | F68: 9 | G68: =(E68*F68-D68*F68)*10000 -> 630000
B69: Feb | C69: Ford | D69: 14 | E69: 20 | F69: 6 | G69: =(E69*F69-D69*F69)*10000 -> 360000
B70: Feb | C70: BMW | D70: 25 | E70: 36 | F70: 6 | G70: =(E70*F70-D70*F70)*10000 -> 660000
B71: Feb | C71: Audi | D71: 30 | E71: 46 | F71: 5 | G71: =(E71*F71-D71*F71)*10000 -> 800000
B72: Mar | C72: Toyota | D72: 16 | E72: 22 | F72: 11 | G72: =(E72*F72-D72*F72)*10000 -> 660000
B73: Mar | C73: Honda | D73: 13 | E73: 20 | F73: 10 | G73: =(E73*F73-D73*F73)*10000 -> 700000
... B86: May | C86: Audi | D86: 33 | E86: 74.625 | F86: 8 | G86: =(E86*F86-D86*F86)*10000 -> 3330000
G87: =SUM(G62:G86) -> 20000000
C91: What if Analysis fn
C94: Intial Investment | D94: 200000
C95: Monthly | D95: 500
C96: Rate of return | D96: 0.07
C97: years | D97: 30
C99: Excepted Amount | D99: =FV(D96/12, D97*12, -D95, -D94) -> 2233285
E101: Table
C103: =FV(D96/12, D97*12, -D95, -D94) -> 2233285 | D103: 0.08 | E103: 0.09 | F103: 0.1 | G103: 0.12
C104: 100 | D104: 2336181.9 | E104: 3129189.6 | F104: 4193528.7 | G104: 7539424.7
C105: 200 | D105: 2485217.8 | E105: 3312263.9 | F105: 4419577.5 | G105: 7888921.1
C106: 1500 | D106: 4422685.1 | E106: 5692230.4 | F106: 7358211.8 | G106: 12432374
C107: 1200 | D107: 3975577.3 | E107: 5143007.4 | F107: 6680065.4 | G107: 11383885
C108: 1900 | D108: 5018828.9 | E108: 6424527.8 | F108: 8262406.9 | G108: 13830360
C109: 2360 | D109: 5704394.2 | E109: 7266669.8 | F109: 9302231.4 | G109: 15438044
C110: 2820 | D110: 6389959.6 | E110: 8108811.8 | F110: 10342056 | G110: 17045727
C111: 3120 | D111: 6837067.4 | E111: 8658034.9 | F111: 11020202 | G111: 18094216
C112: 3740 | D112: 7761090.3 | E112: 9793095.9 | F112: 12421705 | G112: 20261094
C113: 6200 | D113: 11427375 | E113: 14296725 | F113: 17982505 | G113: 28858706

Sheet COLUMN CHART
B2: 8 MODULE
B4: CHARTS
I5: COLUMN CHART
A7: Q1) | B7: Can you create a column chart that displays the quarterly number of shoes sold and the sales for Nike across different regions.
B8: (e.g., North America, Europe, Asia Pacific, Latin America, Middle East) for the year 2023?"
B11: Region | C11: Q1 Sales ($) | D11: Q2 Sales ($) | E11: Q3 Sales ($) | F11: Q4 Sales ($)
B12: North America | C12: 50000 | D12: 55000 | E12: 60000 | F12: 65000
B13: Europe | C13: 40000 | D13: 45000 | E13: 47000 | F13: 50000
B14: Asia Pacific | C14: 35000 | D14: 37000 | E14: 39000 | F14: 42000
B15: Latin America | C15: 20000 | D15: 21000 | E15: 22000 | F15: 23000
B16: Middle East | C16: 15000 | D16: 16000 | E16: 17000 | F16: 18000
A31: Q3) | B31: "Can you create a stacked column chart that illustrates the monthly sales revenue and loss due to expiry of product
I32: STACKED COLUMN CHART
C34: Chocolate company Data
B36: Month | C36: Sales Revenue | D36: loss due to (expired)
B37: January | C37: 50000 | D37: 10000
B38: February | C38: 55000 | D38: 9000
B39: March | C39: 60000 | D39: 7500
B40: April | C40: 65000 | D40: 12500
B41: May | C41: 70000 | D41: 11000
B42: June | C42: 75000 | D42: 10000
B43: July | C43: 80000 | D43: 9000
B44: August | C44: 85000 | D44: 15000
B45: September | C45: 90000 | D45: 14000
B46: October | C46: 95000 | D46: 12500
B47: November | C47: 100000 | D47: 11000
B48: December | C48: 105000 | D48: 10000

Sheet LINE CHART
B2: 8 MODULE
B4: CHARTS
G6: LINE CHART
A8: Q1) | B8: Create a line chart that illustrates the trends in annual supply, demand, and gold prices for the period from 2014 to 2023?"
B10: Year | C10: Supply (tons) | D10: Demand (tons)
B11: 2014 | C11: 2800 | D11: 3000
B12: 2015 | C12: 2750 | D12: 3100
B13: 2016 | C13: 2900 | D13: 3200
B14: 2017 | C14: 3000 | D14: 3300
B15: 2018 | C15: 2950 | D15: 3350
B16: 2019 | C16: 3100 | D16: 3400
B17: 2020 | C17: 3200 | D17: 3450
B18: 2021 | C18: 3150 | D18: 3500
B19: 2022 | C19: 3300 | D19: 3550
B20: 2023 | C20: 3350 | D20: 3600
G31: BAR CHART
A33: Q2) | B33: Make a bar chart of most games sold in gaming industries over 50 decades of time period.
B35: Rank | C35: Title | D35: Units Sold (Million)
B36: #1 | C36: Wii Sports | D36: 82.65
B37: #2 | C37: Super Mario Bros. | D37: 40.24
B38: #3 | C38: Mario Kart Wii | D38: 35.98
B39: #4 | C39: Wii Sport Resort | D39: 32.9
B40: #5 | C40: Pokémon R/G/B | D40: 31.37
B41: #6 | C41: Tetris | D41: 30.26
B42: #7 | C42: New Super Mario Bros. | D42: 29.85
B43: #8 | C43: Wii Play | D43: 28.92
B44: #9 | C44: New Super Mario Bros | D44: 28.51
B45: #10 | C45: Duck Hunt | D45: 28.31
B46: #11 | C46: Nintendogs | D46: 24.68
B47: #12 | C47: Mario Kart DS | D47: 23.26
... B55: #20 | C55: Brain Age | D55: 20.16
G76: SCATTER LINE CHART
A78: Q3) | B78: Make a line chart of daily temperature of Delhi city 2024 9minimum and maimum temperature)
B80: DATE | C80: MIN TEMPERATURE | D80: MAX TEMPERATURE
B81: 45345 | C81: 26.2 | D81: 7.6
B82: 45346 | C82: 24.4 | D82: 8.7
B83: 45347 | C83: 24.6 | D83: 8.3
B84: 45348 | C84: 27 | D84: 9.9
B85: 45349 | C85: 25 | D85: 12.3
B86: 45350 | C86: 25.4 | D86: 10.7
B87: 45351 | C87: 25.5 | D87: 11.4
B88: 45352 | C88: 27.6 | D88: 10.8
B89: 45353 | C89: 29.6 | D89: 15
B90: 45354 | C90: 25.2 | D90: 13.7
B91: 45355 | C91: 26.2 | D91: 9.5
B92: 45356 | C92: 24.9 | D92: 9
... B194: 45458 | C194: 44 | D194: 32.4

Sheet PIE CHART
B2: 8 MODULE
B4: CHARTS
I6: PIE CHART
A8: Q1) | B8: Tanishq Jewellers reported their annual profits for five different types of ornaments. The profits are as follows. Make a pie chart of this report
D10: Yearly Profits of Tanishq Jewellers (in crores)
B12: YEAR | C12: Gold Necklaces | D12: Diamond Rings | E12: Silver Bracelets | F12: Platinum Earrings | G12: Gemstone Pendants
B13: 2023 | C13: 211000000 | D13: 320500000 | E13: 66000000 | F13: 49500000 | G13: 83000000
I37: WATERFALL CHART
A40: Q2) | B40: Growmore Trading reported their monthly returns for the year ,make a visual representation of it in waterfall chart
B42: Month | C42: Return (₹ lakhs)
B43: January | C43: 2500000
B44: February | C44: -1500000
B45: March | C45: 2000000
B46: April | C46: -1000000
B47: May | C47: 3000000
B48: June | C48: -2500000
B49: July | C49: 1800000
B50: August | C50: -1200000
B51: September | C51: 2200000
B52: October | C52: -2000000
B53: November | C53: 2800000
B54: December | C54: -3000000
B56: Visualize these monthly returns using appropriate tools to analyze Growmore Trading's performance throughout the year.

Sheet TEXT FUNCTIONS
C2: 9 MODULE
C4: TEXT FUNCTIONS | L4: POINTS TO BE NOTED
L6: TRIM FN - trim the space from cell
C7: BASIC UNDERSTANDING OF FUNCTIONS | L7: CLEAN - non printable characters
C8: Alexander James Smith | L8: IFERROR - write error whatever we wanted or true or false
C9: functions | D9: USED | L9: REPT - rept the same thing again and again
C10: LEFT | D10: =LEFT(C8,9) -> Alexander | L10: SUBSTITUE - substitue is case senstive
C11: RIGHT | D11: =RIGHT(C8,3) -> ith | L11: LEN - length of txt or number
C12: MID | D12: =MID(C8,11,1) -> J | L12: Evaluate fn in formulas ribbion
C13: FIND | D13: =FIND(" ",C8) -> 10 | L13: bahtext means curreny of thailand
C14: SEARCH | D14: =SEARCH("j",C8) -> 11 | L14: T Fnc used whether data is text or not ( if it is text it show )or (if not empty cell will come)
C15: TODAY | D15: =TODAY() -> 45722 | L15: exact used for find that both text are same or not, and it’s a case sensitive
C16: NOW | D16: =NOW() -> 45722.797 | L16: char help to find charcter of selected cell
C17: CONCATENATE | D17: =CONCATENATE(C8,D13) -> Alexander James Smith10 | L17: use syntax in text function (" ")
C18: FORMULATEXT | D18: =_xlfn.FORMULATEXT(D10) -> =LEFT(C8,9) | L18: we use (INT) fn in age to get round number in age
C19: UPPER | D19: =UPPER(C8) -> ALEXANDER JAMES SMITH
C20: LOWER | D20: =LOWER(C8) -> alexander james smith
C21: PROPER | D21: =PROPER(C8) -> Alexander James Smith
C22: LEN | D22: =LEN(C8) -> 21
C23: REPT | D23: =REPT(D22,5) -> 2121212121
C24: SUBSTITUTE | D24: =SUBSTITUTE(C8,"Alexander","frankrut") -> frankrut James Smith
C25: REPLACE | D25: =REPLACE(C8,1,3,"Robo") -> Roboxander James Smith
C26: inferror fn | D26: =IFERROR(D13<2,) -> FALSE
C27: dollar | D27: =DOLLAR(49,2) -> ₹ 49.00
C28: fixed | D28: =FIXED(34455,1,FALSE) -> 34,455.0
C29: numbervalue | D29: =_xlfn.NUMBERVALUE(D27) -> 49
C30: text | D30: =TEXT(D15,"dd mm yyyy") -> 06 03 2025
C31: t | D31: =T(D27) -> ₹ 49.00
C32: bahttext | D32: =BAHTTEXT(345) -> สามร้อยสี่สิบห้าบาทถ้วน
A33: j | C33: code | D33: =CODE(D28) -> 51
C34: value | D34: =VALUE(D31) -> 49
C35: char | D35: =CHAR(D34) -> 1
C36: exact | D36: =EXACT(E34,D11) -> FALSE
C39: Trim fn
C40: name | D40: Rahul
C41: len | D41: =LEN(D40) -> 13
C42: trim fn | D42: =TRIM(D40) -> Rahul
C43: len | D43: =LEN(D42) -> 5
E46: SOLVE THIS TABLE USING FORMULAS ONLY
B49: name | C49: first space | D49: Second space | E49: lens | F49: difference | G49: first name | H49: Middle name | I49: last name
B51: formulas | C51: =_xlfn.FORMULATEXT(C53) -> =FIND(" ",B53) | D51: =_xlfn.FORMULATEXT(D53) -> =FIND(" ",B53,C53+1) | E51: =_xlfn.FORMULATEXT(E53) -> =LEN(B53) | F51: =_xlfn.FORMULATEXT(F53) -> =D53-C53 | G51: =_xlfn.FORMULATEXT(G53) -> =LEFT(B53,C53-1) | H51: =_xlfn.FORMULATEXT(H53) -> =MID(B53,C53+1,F53) | I51: =_xlfn.FORMULATEXT(I53) -> =MID(B53,D53+1,E53)
B53: Emma Grace Johnson | C53: =FIND(" ",B53) -> 5 | D53: =FIND(" ",B53,C53+1) -> 11 | E53: =LEN(B53) -> 18 | F53: =D53-C53 -> 6 | G53: =LEFT(B53,C53-1) -> Emma | H53: =MID(B53,C53+1,F53) -> Grace | I53: =MID(B53,D53+1,E53) -> Johnson
B54: Liam Michael Brown | C54: =FIND(" ",B54) -> 5 | D54: =FIND(" ",B54,C54+1) -> 13 | E54: =LEN(B54) -> 18 | F54: =D54-C54 -> 8 | G54: =LEFT(B54,C54-1) -> Liam | H54: =MID(B54,C54+1,F54) -> Michael | I54: =MID(B54,D54+1,E54) -> Brown
B55: Olivia Smith | C55: =FIND(" ",B55) -> 7 | E55: =LEN(B55) -> 12 | G55: =LEFT(B55,C55-1) -> Olivia | H55: =MID(B55,C55+1,F55) | I55: =MID(B55,C55+1,E55) -> Smith
B56: Noah James Williams | C56: =FIND(" ",B56) -> 5 | D56: =FIND(" ",B56,C56+1) -> 11 | E56: =LEN(B56) -> 19 | F56: =D56-C56 -> 6 | G56: =LEFT(B56,C56-1) -> Noah | H56: =MID(B56,C56+1,F56) -> James | I56: =MID(B56,D56+1,E56) -> Williams
B57: Ava Davis | C57: =FIND(" ",B57) -> 4 | E57: =LEN(B57) -> 9 | G57: =LEFT(B57,C57-1) -> Ava | H57: =MID(B57,C57+1,F57) | I57: =MID(B57,D57+1,E57) -> Ava Davis
B58: Sophia Marie Martinez | C58: =FIND(" ",B58) -> 7 | D58: =FIND(" ",B58,C58+1) -> 13 | E58: =LEN(B58) -> 21 | F58: =D58-C58 -> 6 | G58: =LEFT(B58,C58-1) -> Sophia | H58: =MID(B58,C58+1,F58) -> Marie | I58: =MID(B58,D58+1,E58) -> Martinez
B59: Elijah Robert Anderson | C59: =FIND(" ",B59) -> 7 | D59: =FIND(" ",B59,C59+1) -> 14 | E59: =LEN(B59) -> 22 | F59: =D59-C59 -> 7 | G59: =LEFT(B59,C59-1) -> Elijah | H59: =MID(B59,C59+1,F59) -> Robert | I59: =MID(B59,D59+1,E59) -> Anderson
B60: Isabella Thomas | C60: =FIND(" ",B60) -> 9 | E60: =LEN(B60) -> 15 | G60: =LEFT(B60,C60-1) -> Isabella | H60: =MID(B60,C60+1,F60) | I60: =MID(B60,C60+1,E60) -> Thomas
B61: Lucas Alexander Hernandez | C61: =FIND(" ",B61) -> 6 | D61: =FIND(" ",B61,C61+1) -> 16 | E61: =LEN(B61) -> 25 | F61: =D61-C61 -> 10 | G61: =LEFT(B61,C61-1) -> Lucas | H61: =MID(B61,C61+1,F61) -> Alexander | I61: =MID(B61,D61+1,E61) -> Hernandez
B62: Mia Elizabeth Moore | C62: =FIND(" ",B62) -> 4 | D62: =FIND(" ",B62,C62+1) -> 14 | E62: =LEN(B62) -> 19 | F62: =D62-C62 -> 10 | G62: =LEFT(B62,C62-1) -> Mia | H62: =MID(B62,C62+1,F62) -> Elizabeth | I62: =MID(B62,D62+1,E62) -> Moore
B69: Dataset:
B71: We will generate a dataset with the following columns:
B73: 1. Employee ID: A unique identifier for each employee.
B74: 2. Full Name: The full name of the employee.
B75: 3. Date of Birth: The employee's birthdate.
B76: 4. Monthly Salary (THB): The monthly salary of the employee.
B77: 5. Hire Date: The date the employee was hired.
B78: 6. Department Code: A code representing the department the employee works in.
B81: Complex Problem:
B83: Given this dataset, we will create a report that uses all the specified functions in Excel.
B85: 1. Employee Initials: Use the LEFT, RIGHT, MID, FIND functions to extract the initials from the full name.
B86: 2. Age:Use the TODAY function to calculate the current date and subtract the date of birth to get the age of the employee.
... B93: 9. Text Representation:Use the T function to return the text from a value.
B97: Employee ID | C97: Full Name | D97: Date of Birth | E97: Monthly Salary (THB) | F97: Hire Date | G97: Department Code
B98: E001 | C98: John Michael Doe | D98: 31182 | E98: 30000 | F98: 40330 | G98: D001
B99: E002 | C99: Jane Elizabeth Smith | D99: 33110 | E99: 45000.5 | F99: 42200 | G99: D002
B100: E003 | C100: Michael James Johnson | D100: 30260 | E100: 50000.75 | F100: 39527 | G100: D003
B101: E004 | C101: Emily Ann Brown | D101: 32621 | E101: 38000.25 | F101: 41218 | G101: D004
B102: E005 | C102: William David Williams | D102: 27594 | E102: 55000 | F102: 38367 | G102: D005
B103: E006 | C103: Linda Maria Taylor | D103: 34150 | E103: 40000.3 | F103: 41871 | G103: D006
B104: E007 | C104: James Robert Anderson | D104: 32216 | E104: 47000.45 | F104: 40688 | G104: D007
B105: E008 | C105: Patricia Anne Martinez | D105: 29190 | E105: 42000.6 | F105: 38990 | G105: D008
B106: E009 | C106: Robert John Hernandez | D106: 29877 | E106: 50000.75 | F106: 39882 | G106: D009
B107: E010 | C107: Sarah Jessica Lee | D107: 34707 | E107: 32000.8 | F107: 42786 | G107: D010
B108: E011 | C108: Charles Anthony Lopez | D108: 31651 | E108: 45000 | F108: 40882 | G108: D001
B109: E012 | C109: Barbara Ann Gonzalez | D109: 31008 | E109: 47000.1 | F109: 40344 | G109: D002
... B197: E100 | C197: Lisa Marie Davis | D197: 35051 | E197: 42200 | F197: 42957 | G197: D010
B200: Age | C200: first name | D200: mid name | E200: last name | F200: Proper form | G200: Dollar currency | H200: T function | I200: Combine(DC+ID+AGE) | J200: Hire Date
B201: =ROUNDUP((TODAY()-D98)/365.5,1) -> 39.8 | C201: =LEFT(C98,FIND(" ",C98)) -> John | D201: =MID(C98,(FIND(" ",C98)+1),(FIND(" ",C98,FIND(" ",C98)+1))-(FIND(" ",C98))) -> Michael | E201: =RIGHT(C98,LEN(C98)-FIND(" ", C98, FIND(" ", C98) + 1)) -> Doe | F201: =PROPER(C98) -> John Michael Doe | G201: =DOLLAR(E98,0) -> ₹ 30,000 | H201: =T(G201) -> ₹ 30,000 | I201: =CONCATENATE(G98,B98,B201) -> D001E00139.8 | J201: =TEXT(F98," dd mmm yyyy") -> 01 Jun 2010
B202: =ROUNDUP((TODAY()-D99)/365.5,1) -> 34.6 | C202: =LEFT(C99,FIND(" ",C99)) -> Jane | D202: =MID(C99,(FIND(" ",C99)+1),(FIND(" ",C99,FIND(" ",C99)+1))-(FIND(" ",C99))) -> Elizabeth | E202: =RIGHT(C99,LEN(C99)-FIND(" ", C99, FIND(" ", C99) + 1)) -> Smith | F202: =PROPER(C99) -> Jane Elizabeth Smith | G202: =DOLLAR(E99,0) -> ₹ 45,001 | H202: =T(G202) -> ₹ 45,001 | I202: =CONCATENATE(G99,B99,B202) -> D002E00234.6 | J202: =TEXT(F99," dd mmm yyyy") -> 15 Jul 2015
B203: =ROUNDUP((TODAY()-D100)/365.5,1) -> 42.4 | C203: =LEFT(C100,FIND(" ",C100)) -> Michael | D203: =MID(C100,(FIND(" ",C100)+1),(FIND(" ",C100,FIND(" ",C100)+1))-(FIND(" ",C100))) -> James | E203: =RIGHT(C100,LEN(C100)-FIND(" ", C100, FIND(" ", C100) + 1)) -> Johnson | F203: =PROPER(C100) -> Michael James Johnson | G203: =DOLLAR(E100,0) -> ₹ 50,001 | H203: =T(G203) -> ₹ 50,001 | I203: =CONCATENATE(G100,B100,B203) -> D003E00342.4 | J203: =TEXT(F100," dd mmm yyyy") -> 20 Mar 2008
B204: =ROUNDUP((TODAY()-D101)/365.5,1) -> 35.9 | C204: =LEFT(C101,FIND(" ",C101)) -> Emily | D204: =MID(C101,(FIND(" ",C101)+1),(FIND(" ",C101,FIND(" ",C101)+1))-(FIND(" ",C101))) -> Ann | E204: =RIGHT(C101,LEN(C101)-FIND(" ", C101, FIND(" ", C101) + 1)) -> Brown | F204: =PROPER(C101) -> Emily Ann Brown | G204: =DOLLAR(E101,0) -> ₹ 38,000 | H204: =T(G204) -> ₹ 38,000 | I204: =CONCATENATE(G101,B101,B204) -> D004E00435.9 | J204: =TEXT(F101," dd mmm yyyy") -> 05 Nov 2012
B205: =ROUNDUP((TODAY()-D102)/365.5,1) -> 49.6 | C205: =LEFT(C102,FIND(" ",C102)) -> William | D205: =MID(C102,(FIND(" ",C102)+1),(FIND(" ",C102,FIND(" ",C102)+1))-(FIND(" ",C102))) -> David | E205: =RIGHT(C102,LEN(C102)-FIND(" ", C102, FIND(" ", C102) + 1)) -> Williams | F205: =PROPER(C102) -> William David Williams | G205: =DOLLAR(E102,0) -> ₹ 55,000 | H205: =T(G205) -> ₹ 55,000 | I205: =CONCATENATE(G102,B102,B205) -> D005E00549.6 | J205: =TEXT(F102," dd mmm yyyy") -> 15 Jan 2005
B206: =ROUNDUP((TODAY()-D103)/365.5,1) -> 31.7 | C206: =LEFT(C103,FIND(" ",C103)) -> Linda | D206: =MID(C103,(FIND(" ",C103)+1),(FIND(" ",C103,FIND(" ",C103)+1))-(FIND(" ",C103))) -> Maria | E206: =RIGHT(C103,LEN(C103)-FIND(" ", C103, FIND(" ", C103) + 1)) -> Taylor | F206: =PROPER(C103) -> Linda Maria Taylor | G206: =DOLLAR(E103,0) -> ₹ 40,000 | H206: =T(G206) -> ₹ 40,000 | I206: =CONCATENATE(G103,B103,B206) -> D006E00631.7 | J206: =TEXT(F103," dd mmm yyyy") -> 20 Aug 2014
B207: =ROUNDUP((TODAY()-D104)/365.5,1) -> 37 | C207: =LEFT(C104,FIND(" ",C104)) -> James | D207: =MID(C104,(FIND(" ",C104)+1),(FIND(" ",C104,FIND(" ",C104)+1))-(FIND(" ",C104))) -> Robert | E207: =RIGHT(C104,LEN(C104)-FIND(" ", C104, FIND(" ", C104) + 1)) -> Anderson | F207: =PROPER(C104) -> James Robert Anderson | G207: =DOLLAR(E104,0) -> ₹ 47,000 | H207: =T(G207) -> ₹ 47,000 | I207: =CONCATENATE(G104,B104,B207) -> D007E00737 | J207: =TEXT(F104," dd mmm yyyy") -> 25 May 2011
B208: =ROUNDUP((TODAY()-D105)/365.5,1) -> 45.3 | C208: =LEFT(C105,FIND(" ",C105)) -> Patricia | D208: =MID(C105,(FIND(" ",C105)+1),(FIND(" ",C105,FIND(" ",C105)+1))-(FIND(" ",C105))) -> Anne | E208: =RIGHT(C105,LEN(C105)-FIND(" ", C105, FIND(" ", C105) + 1)) -> Martinez | F208: =PROPER(C105) -> Patricia Anne Martinez | G208: =DOLLAR(E105,0) -> ₹ 42,001 | H208: =T(G208) -> ₹ 42,001 | I208: =CONCATENATE(G105,B105,B208) -> D008E00845.3 | J208: =TEXT(F105," dd mmm yyyy") -> 30 Sep 2006
B209: =ROUNDUP((TODAY()-D106)/365.5,1) -> 43.4 | C209: =LEFT(C106,FIND(" ",C106)) -> Robert | D209: =MID(C106,(FIND(" ",C106)+1),(FIND(" ",C106,FIND(" ",C106)+1))-(FIND(" ",C106))) -> John | E209: =RIGHT(C106,LEN(C106)-FIND(" ", C106, FIND(" ", C106) + 1)) -> Hernandez | F209: =PROPER(C106) -> Robert John Hernandez | G209: =DOLLAR(E106,0) -> ₹ 50,001 | H209: =T(G209) -> ₹ 50,001 | I209: =CONCATENATE(G106,B106,B209) -> D009E00943.4 | J209: =TEXT(F106," dd mmm yyyy") -> 10 Mar 2009
B210: =ROUNDUP((TODAY()-D107)/365.5,1) -> 30.2 | C210: =LEFT(C107,FIND(" ",C107)) -> Sarah | D210: =MID(C107,(FIND(" ",C107)+1),(FIND(" ",C107,FIND(" ",C107)+1))-(FIND(" ",C107))) -> Jessica | E210: =RIGHT(C107,LEN(C107)-FIND(" ", C107, FIND(" ", C107) + 1)) -> Lee | F210: =PROPER(C107) -> Sarah Jessica Lee | G210: =DOLLAR(E107,0) -> ₹ 32,001 | H210: =T(G210) -> ₹ 32,001 | I210: =CONCATENATE(G107,B107,B210) -> D010E01030.2 | J210: =TEXT(F107," dd mmm yyyy") -> 20 Feb 2017
B211: =ROUNDUP((TODAY()-D108)/365.5,1) -> 38.5 | C211: =LEFT(C108,FIND(" ",C108)) -> Charles | D211: =MID(C108,(FIND(" ",C108)+1),(FIND(" ",C108,FIND(" ",C108)+1))-(FIND(" ",C108))) -> Anthony | E211: =RIGHT(C108,LEN(C108)-FIND(" ", C108, FIND(" ", C108) + 1)) -> Lopez | F211: =PROPER(C108) -> Charles Anthony Lopez | G211: =DOLLAR(E108,0) -> ₹ 45,000 | H211: =T(G211) -> ₹ 45,000 | I211: =CONCATENATE(G108,B108,B211) -> D001E01138.5 | J211: =TEXT(F108," dd mmm yyyy") -> 05 Dec 2011
B212: =ROUNDUP((TODAY()-D109)/365.5,1) -> 40.3 | C212: =LEFT(C109,FIND(" ",C109)) -> Barbara | D212: =MID(C109,(FIND(" ",C109)+1),(FIND(" ",C109,FIND(" ",C109)+1))-(FIND(" ",C109))) -> Ann | E212: =RIGHT(C109,LEN(C109)-FIND(" ", C109, FIND(" ", C109) + 1)) -> Gonzalez | F212: =PROPER(C109) -> Barbara Ann Gonzalez | G212: =DOLLAR(E109,0) -> ₹ 47,000 | H212: =T(G212) -> ₹ 47,000 | I212: =CONCATENATE(G109,B109,B212) -> D002E01240.3 | J212: =TEXT(F109," dd mmm yyyy") -> 15 Jun 2010
... B300: =ROUNDUP((TODAY()-D197)/365.5,1) -> 29.2 | C300: =LEFT(C197,FIND(" ",C197)) -> Lisa | D300: =MID(C197,(FIND(" ",C197)+1),(FIND(" ",C197,FIND(" ",C197)+1))-(FIND(" ",C197))) -> Marie | E300: =RIGHT(C197,LEN(C197)-FIND(" ", C197, FIND(" ", C197) + 1)) -> Davis | F300: =PROPER(C197) -> Lisa Marie Davis | G300: =DOLLAR(E197,0) -> ₹ 42,200 | H300: =T(G300) -> ₹ 42,200 | I300: =CONCATENATE(G197,B197,B300) -> D010E10029.2 | J300: =TEXT(F197," dd mmm yyyy") -> 10 Aug 2017

Sheet MATHEMATICAL FUNCTIONS
B3: 10 MODULE
B5: MATHEMATICAL FUNCTIONS | M5: Points to be Noted
M8: count fn only counts numericals numbers
B9: BASIC UNDERSTANDING | M9: countif used for giving conditions (only 1)
B10: Sample Data 1 | F10: SAMPLE DATA 2 | M10: countifs used for giving two conditions
B11: FUNCTIONS | C11: 206 | M11: counta counts text and numbers both and aslo count empty cell in multiple columns
C12: 41 | G12: 164
C13: 185 | G13: b | M13: sum fn only sums numericals numbers
C14: 132 | G14: 423 | M14: sumif used for giving conditions (only 1)
C15: 145 | G15: 373 | M15: sumifs used for giving two conditions
C16: 238
C17: 34 | G17: 415 | M17: power used to find exponential power of numbers, ex
C18: 197 | G18: 61 | M18: POWER(2, 3) results in 8 (because 2x2x2=8)
C19: 241 | G19: 271
C20: 173 | G20: 32 | M20: Sqrt = help to find the square of a number ,ex
C21: 146 | G21: 238 | M21: sqrt(9) = 3
B22: SUM | C22: =SUM(C11:C21) -> 1738 | F22: Count | G22: =COUNT(G12:G21) -> 8
B23: AVERAGE | C23: =AVERAGE(C11:C21) -> 158 | F23: CountA | G23: =COUNTA(G12:G21) -> 9 | M23: mean = average
B24: MIN | C24: =MIN(C11:C21) -> 34 | F24: SUM | G24: =SUM(G12:G21) -> 1977 | M24: median = The middle value in a list of numbers
B25: MAX | C25: =MAX(C11:C21) -> 241 | F25: AVERAGE | G25: =AVERAGE(G12:G21) -> 247.125 | M25: mode = The number that appears most frequently in a list.
M26: {=MODE.SNGL(range) (for a single mode) or =MODE.MULT(range) for multiples}
M28: we should always write text in inverted commas
M30: DGET = number error(if answer have more than 1)
B35: Sample Data 3
B37: Team | C37: Points | D37: Date
B38: Team A | C38: 85 | D38: 45292
B39: Team B | C39: 90 | D39: 45293
B40: Team A | C40: 78 | D40: 45294
B41: Team C | C41: 92 | D41: 45292
B42: Team B | C42: 88 | D42: 45295
B43: Team A | C43: 80 | D43: 45296
B44: Team C | C44: 95 | D44: 45293
B45: Team B | C45: 86 | D45: 45294
B46: Team C | C46: 91 | D46: 45295
B49: Task
B50: 1. Calculate the total points scored by Team A.
B51: 2. Determine the total points scored by Team B between 2024-01-01 and 2024-01-03.
B52: 3. Count the number of entries where Team C has scored points.
B53: 4. Count the number of entries for Team A between 2024-01-01 and 2024-01-05.
B54: 5. Find the average points scored by Team B.
B55: 6. Calculate the average points scored by Team C between 2024-01-01 and 2024-01-04.
B56: 7. Determine the maximum points scored in the dataset.
B57: 8. Find the minimum points scored in the dataset.
B58: 9. Retrieve the points scored by Team B on 2024-01-03.
B59: 10. Calculate the subtotal of points, considering only visible rows in a filtered dataset.
B60: 11. Determine how many blank cells are in the Points column.
... B64: Function
B65: SUMIF | C65: =SUMIF(B38:B46,"Team A",C38:C46) -> 243
B66: SUMIFS | C66: =SUMIFS(C38:C46,B38:B46,"TEAM B",D38:D46,">=01-01-2024",D38:D46,"<=05-01-2024") -> 264
B67: COUNTIF | C67: =COUNTIF(B38:C46,"Team C") -> 3
B68: COUNTIFS | C68: =COUNTIFS(B38:B46,"team A",D38:D46,">=01-01-2024",D38:D46,"=<05-01-2024") -> 0
B69: AVERAGEIF | C69: =AVERAGEIF(B38:B46,"Team B",C38:C46) -> 88
B70: AVERAGEIFS | C70: =AVERAGEIFS(C38:C46,B38:B46,"team C",D38:D46,">=01-01-2024",D38:D46,"<=05-01-2024") -> 92.666667
B71: DMax | C71: =DMAX(B37:D46,"POINTS",E70:E71) -> 95
B72: DMin | C72: =DMIN(B37:D46,"POINTS",E71:E72) -> 78
B73: DGET | C73: DGET(B30:D38)
B74: SUBTOTAL | C74: cell C28
B75: COUNTBLANK | C75: =COUNTBLANK(C38:C46) -> 0
B76: ISTEXT | C76: =ISTEXT(C38:C46) -> FALSE
B79: Question
B80: You are given the following sales data for various products in different regions and months. Calculate the following using formula
B82: 1. The total sales for all products.
B83: 2. The total sales for "Apples".
B84: 3. The total sales for "Oranges" in the "North" region.
B85: 4. The total sales for "Bananas" in the "South" region in the month of "March".
B88: Product | C88: Sales | D88: Region | E88: Month
B89: Apples | C89: 120 | D89: North | E89: January
B90: Oranges | C90: 150 | D90: South | E90: January
B91: Bananas | C91: 200 | D91: North | E91: February
B92: Apples | C92: 180 | D92: South | E92: February
B93: Oranges | C93: 220 | D93: North | E93: March
B94: Bananas | C94: 160 | D94: South | E94: March
B95: Apples | C95: 140 | D95: North | E95: March
B96: Oranges | C96: 210 | D96: South | E96: April
B97: Bananas | C97: 190 | D97: North | E97: April
B100: Solution
B102: Heading | C102: Answer | D102: formula
B104: total sales of all products | C104: =SUM(C89:C97) -> 1570 | D104: =_xlfn.FORMULATEXT(C104) -> =SUM(C89:C97)
B106: total sales of apples | C106: =SUMIF(B89:B97,"apples",C89:C97) -> 440 | D106: =_xlfn.FORMULATEXT(C106) -> =SUMIF(B89:B97,"apples",C89:C97)
B108: sale of oranges in north | C108: =SUMIFS(C89:C97,B89:B97,"oranges",D89:D97,"North") -> 220 | D108: =_xlfn.FORMULATEXT(C108) -> =SUMIFS(C89:C97,B89:B97,"oranges",D89:D97,"North")
B110: sale of bananas in south in march | C110: =SUMIFS(C89:C97,B89:B97,"bananas",D89:D97,"south",E89:E97,"march") -> 160 | D110: =_xlfn.FORMULATEXT(C110) -> =SUMIFS(C89:C97,B89:B97,"bananas",D89:D97,"south",E89:E97,"march")
B114: Question
B115: You are given the following dataset of car companies, their sales, the regions they were sold in, and the sale status. Calculate the following the formulas
B117: 1. The total number of sales entries.
B118: 2. The total number of non-empty cells in the "Car Company" column.
B119: 3. The number of sales entries for "Toyota".
B120: 4. The number of sales entries for "Ford" in the "East" region.
B121: 5. The number of sales entries that were "Completed" in the "West" region.
B124: Car Company | C124: Sales | D124: Region | E124: Status
B125: Toyota | C125: 120 | D125: North | E125: Completed
B126: Ford | C126: 150 | D126: South | E126: Pending
B127: Honda | D127: North | E127: Completed
B128: Toyota | C128: 180 | D128: East | E128: Completed
B129: Ford | C129: 220 | D129: North | E129: Completed
B130: Toyota | C130: 200 | D130: West | E130: Pending
B131: Honda | C131: 130 | D131: East | E131: Completed
B132: Ford | C132: 175 | D132: West | E132: Completed
B133: Toyota | C133: 160 | D133: East | E133: Completed
B134: Honda | C134: 140 | D134: South | E134: Pending
B136: Solution
...

Sheet LOGICAL FUNCTIONS
B2: 11 MODULE
B4: LOGICAL & DATE/TIME FUNCTIONS
B7: LOGICAL FUNCTIONS
B10: Sample Data:
B12: Employee | C12: Hours Worked | D12: Project Deadline Met | E12: Overtime Hours | F12: Department
B13: John | C13: 40 | D13: Yes | E13: 5 | F13: Sales
B14: Alice | C14: 35 | D14: No | E14: 2 | F14: Marketing
B15: Bob | C15: 45 | D15: Yes | E15: 10 | F15: IT
B16: Carol | C16: 50 | D16: Yes | E16: 0 | F16: IT
B17: Dave | C17: 30 | D17: No | E17: 8 | F17: Sales
B18: Eve | C18: 38 | D18: Yes | E18: 4 | F18: Marketing
B19: Frank | C19: 42 | D19: No | E19: 6 | F19: IT
B22: Task Number | C22: Task Description
B23: 1 | C23: Check if the employee worked more than 40 hours.
B24: 2 | C24: Determine if an employee worked more than 40 hours and met the project deadline.
B25: 3 | C25: Check if an employee worked more than 40 hours and has more than 5 overtime hours.
B26: 4 | C26: Determine if an employee either worked more than 40 hours or has more than 5 overtime hours.
B27: 5 | C27: Check if an employee worked more than 40 hours and is in the IT department.
B28: 6 | C28: Determine if an employee worked more than 40 hours or is in the Marketing department.
B29: 7 | C29: Check if an employee did not meet the project deadline
B32: TASK NO | C32: 1 | D32: 2 | E32: 3 | F32: 4 | G32: 5 | H32: 6 | I32: 7
B33: FUNCTIONS USED | C33: if condition | D33: NESTED IF | E33: AND | F33: OR | G33: IF WITH AND | H33: IF WITH OR | I33: IF WITH NOT
B34: 1 | C34: =IF($C13>40,"YES","NO") -> NO | D34: =IF($C13>40,"YES",IF(D13="YES","MET","NOT MET")) -> MET | E34: =AND(C13>40,E13>5) -> FALSE | F34: =IF(OR(C13>40,E13>5),"YES","NO") -> NO | G34: =IF(AND(C13>40,F13="IT"),"YES","NO") -> NO | H34: =IF(OR(C13>40,F13="Marketing"),"Yes","No") -> No | I34: =IF(NOT(D13="yes"),"met","not met") -> not met
B35: 2 | C35: =IF($C14>40,"YES","NO") -> NO | D35: =IF($C14>40,"YES",IF(D14="YES","MET","NOT MET")) -> NOT MET | E35: =AND(C14>40,E14>5) -> FALSE | F35: =IF(OR(C14>40,E14>5),"YES","NO") -> NO | G35: =IF(AND(C14>40,F14="IT"),"YES","NO") -> NO | H35: =IF(OR(C14>40,F14="Marketing"),"Yes","No") -> Yes | I35: =IF(NOT(D14="yes"),"met","not met") -> met
B36: 3 | C36: =IF($C15>40,"YES","NO") -> YES | D36: =IF($C15>40,"YES",IF(D15="YES","MET","NOT MET")) -> YES | E36: =AND(C15>40,E15>5) -> TRUE | F36: =IF(OR(C15>40,E15>5),"YES","NO") -> YES | G36: =IF(AND(C15>40,F15="IT"),"YES","NO") -> YES | H36: =IF(OR(C15>40,F15="Marketing"),"Yes","No") -> Yes | I36: =IF(NOT(D15="yes"),"met","not met") -> not met
B37: 4 | C37: =IF($C16>40,"YES","NO") -> YES | D37: =IF($C16>40,"YES",IF(D16="YES","MET","NOT MET")) -> YES | E37: =AND(C16>40,E16>5) -> FALSE | F37: =IF(OR(C16>40,E16>5),"YES","NO") -> YES | G37: =IF(AND(C16>40,F16="IT"),"YES","NO") -> YES | H37: =IF(OR(C16>40,F16="Marketing"),"Yes","No") -> Yes | I37: =IF(NOT(D16="yes"),"met","not met") -> not met
B38: 5 | C38: =IF($C17>40,"YES","NO") -> NO | D38: =IF($C17>40,"YES",IF(D17="YES","MET","NOT MET")) -> NOT MET | E38: =AND(C17>40,E17>5) -> FALSE | F38: =IF(OR(C17>40,E17>5),"YES","NO") -> YES | G38: =IF(AND(C17>40,F17="IT"),"YES","NO") -> NO | H38: =IF(OR(C17>40,F17="Marketing"),"Yes","No") -> No | I38: =IF(NOT(D17="yes"),"met","not met") -> met
B39: 6 | C39: =IF($C18>40,"YES","NO") -> NO | D39: =IF($C18>40,"YES",IF(D18="YES","MET","NOT MET")) -> MET | E39: =AND(C18>40,E18>5) -> FALSE | F39: =IF(OR(C18>40,E18>5),"YES","NO") -> NO | G39: =IF(AND(C18>40,F18="IT"),"YES","NO") -> NO | H39: =IF(OR(C18>40,F18="Marketing"),"Yes","No") -> Yes | I39: =IF(NOT(D18="yes"),"met","not met") -> not met
B40: 7 | C40: =IF($C19>40,"YES","NO") -> YES | D40: =IF($C19>40,"YES",IF(D19="YES","MET","NOT MET")) -> YES | E40: =AND(C19>40,E19>5) -> TRUE | F40: =IF(OR(C19>40,E19>5),"YES","NO") -> YES | G40: =IF(AND(C19>40,F19="IT"),"YES","NO") -> YES | H40: =IF(OR(C19>40,F19="Marketing"),"Yes","No") -> Yes | I40: =IF(NOT(D19="yes"),"met","not met") -> met
B43: DATE & TIME FUNCTIONS
B46: Sample Data:
B48: Event | C48: Start Date | D48: End Date | E48: Start Time | F48: End Time | G48: text format
B49: Project Kickoff | C49: 45505 | D49: 45514 | E49: 0.375 | F49: 0.70833333 | G49: 01-08-2024
B50: Midterm Review | C50: 45519 | D50: 45520 | E50: 0.41666667 | F50: 0.625 | G50: 09:00:00
B51: Final Deadline | C51: 45534 | D51: 45537 | E51: 0.33333333 | F51: 0.75
B54: Task Number | C54: Task Description
B55: 1 | C55: Get Today’s Date
B56: 2 | C56: Get the Current Date and Time
B57: 3 | C57: Extract the Day from the Start Date of the Project Kickoff
B58: 4 | C58: Extract the Month from the Start Date of the Project Kickoff
B59: 5 | C59: Extract the Year from the Start Date of the Project Kickoff
B60: 6 | C60: Convert the Start Date of the Project Kickoff to a Date Value
B61: 7 | C61: Convert the Start Time of the Project Kickoff to a Time Value
B62: 8 | C62: Get the Hour of the Start Time of the Project Kickoff
B63: 9 | C63: Get the Minutes of the Start Time of the Project Kickoff
B64: 10 | C64: Get the Seconds of the Start Time of the Project Kickoff
B65: 11 | C65: Calculate the Number of Days between the End Date and Start Date of the Project Kickoff
B66: 12 | C66: Calculate the Difference in Days between the End Date and Start Date using the DAY360 Method
... B77: 23 | C77: Calculate the Fraction of the Year between the Start Date and End Date
B81: TASK | C81: FUNCTIONS | D81: SOLUTIONS | E81: POINTS TO REMEMBER
B82: 1 | C82: TODAY | D82: =TODAY() -> 45722
B83: 2 | C83: NOW | D83: =NOW() -> 45722.797
B84: 3 | C84: DAY | D84: =DAY(C49) -> 1
B85: 4 | C85: MONTH | D85: =MONTH(C51-C49) -> 1
B86: 5 | C86: YEAR | D86: =YEAR(C49) -> 2024
B87: 6 | C87: DATE | D87: =DATE(2024,8,1) -> 45505
B88: 7 | C88: TIME | D88: =TIMEVALUE(G50) -> 0.375
B89: 8 | C89: HOUR | D89: =HOUR(E49) -> 9
B90: 9 | C90: MINUTES | D90: =MINUTE(E49) -> 0
B91: 10 | C91: SECONDS | D91: =SECOND(E49) -> 0
B92: 11 | C92: DAYS | D92: =_xlfn.DAYS(D49,C49) -> 9
B93: 12 | C93: DAY360 | D93: =DAYS360(C49,D49) -> 9
B94: 13 | C94: WEEKDAY | D94: =WEEKDAY(C49,1) -> 5
B95: 14 | C95: WEEKNUM | D95: =WEEKNUM(C49) -> 31
B96: 15 | C96: DATEVALUE | D96: =DATEVALUE(G49) -> 45505
B97: 16 | C97: TIMEVALUE | D97: =TIMEVALUE(G50) -> 0.375
B98: 17 | C98: NETWORKDAYS | D98: =NETWORKDAYS(C49,D49) -> 7 | E98: default holidays
B99: 18 | C99: NETWORKDAYS,INTL | D99: =NETWORKDAYS.INTL(C49,D49,7) -> 6 | E99: for international holidays
B100: 19 | C100: WORKDAY | D100: =WORKDAY(D49,1) -> 45516 | E100: workday started from 0
B101: 20 | C101: WORKDAY.INTL | D101: =WORKDAY.INTL(D49,1,7) -> 45515 | E101: for international holidays
B102: 21 | C102: EOMONTH | D102: =EOMONTH(D49,0) -> 45535 | E102: End of the month
B103: 22 | C103: EDATE | D103: =EDATE(C49,1) -> 45536 | F103: usually used for trackers
B104: 23 | C104: YEARFRAC | D104: =YEARFRAC(C49,D49) -> 0.025
B108: Question: 1
B110: You are given a table of customers with their age, student status, and amount spent. Determine if each customer qualifies for a special discount using the criteria:
B112: 1. The customer must be either a senior citizen (age 65 or older) or a student (with a valid student ID).
B113: 2. The customer must have spent at least $100 in the store.
B115: Fill out the "Qualifies for Discount" column with TRUE if the customer qualifies for the discount and FALSE otherwise.
B117: Sample Data:
B119: Age | C119: Student (Y/N) | D119: Amount Spent | E119: Qualifies for Discount
B120: 70 | C120: N | D120: 120 | E120: =IF(AND(OR(B120>=65,C120="Y"),(D120>=100)),"True","false") -> True
B121: 20 | C121: Y | D121: 90 | E121: =IF(AND(OR(B121>=65,C121="Y"),(D121>=100)),"True","false") -> false
B122: 22 | C122: N | D122: 150 | E122: =IF(AND(OR(B122>=65,C122="Y"),(D122>=100)),"True","false") -> false
B123: 66 | C123: Y | D123: 200 | E123: =IF(AND(OR(B123>=65,C123="Y"),(D123>=100)),"True","false") -> True
B124: 64 | C124: N | D124: 80 | E124: =IF(AND(OR(B124>=65,C124="Y"),(D124>=100)),"True","false") -> false
B125: 18 | C125: Y | D125: 110 | E125: =IF(AND(OR(B125>=65,C125="Y"),(D125>=100)),"True","false") -> True
B128: You are an analyst for a large retail company, and you need to identify top-performing products based on several criteria.
B129: You have a large dataset with sales data for different products across various stores. Your task is to determine if a product qualifies as a "Top Performer".
B131: The criteria for a product to be considered a "Top Performer" are:
B132: 1. The product must have total sales exceeding $1,000,000.
B133: 2. The product must have been sold in at least 10 stores.
B134: 3. If the product is in the "Electronics" category, it must have an average customer rating of at least 4.5.
B135: 4. If the product is in the "Furniture" category, it must have a return rate of less than 5%.
B138: Question
B140: Fill in the table below with sample data and then write an Excel formula using the IF, AND, and OR functions to determine if a product qualifies as a "Top Performer".
B141: The formula should return "Top Performer" if the product qualifies and "Not a Top Performer" if it does not.
B143: Product Name | C143: Total Sales ($) | D143: Number of Stores | E143: Customer Rating | F143: Return Rate (%) | G143: Category | H143: 1 TASK | I143: 2 TASK | J143: 3 TASK | K143: 4 TASK
B144: Product A | C144: 1200000 | D144: 15 | E144: 4.7 | F144: 0.02 | G144: Electronics | H144: =IF(C144>1000000,"cross 1 million","Did not cross 1 million") -> cross 1 million | I144: =IF(D144>=10,"sold more than 10 stores","did not sold more then 10 stores") -> sold more than 10 stores | J144: =IF(AND(G144 = "Electronics",AVERAGE(E144:E149)>4.5),"high rating Product","Average rating Product") -> high rating Product | K144: =IF(AND(G144 = "Furniture",F144>5%),"long term use product","short term use product") -> short term use product
B145: Product B | C145: 900000 | D145: 8 | E145: 4.8 | F145: 0.01 | G145: Furniture | H145: =IF(C145>1000000,"cross 1 million","Did not cross 1 million") -> Did not cross 1 million | I145: =IF(D145>=10,"sold more than 10 stores","did not sold more then 10 stores") -> did not sold more then 10 stores | J145: =IF(AND(G145 = "Electronics",AVERAGE(E145:E149)>4.5),"high rating Product","Average rating Product") -> Average rating Product | K145: =IF(AND(G145 = "Furniture",F145>5%),"long term use product","short term use product") -> short term use product
B146: Product D | C146: 2000000 | D146: 20 | E146: 4.9 | F146: 0.06 | G146: Groceries | H146: =IF(C146>1000000,"cross 1 million","Did not cross 1 million") -> cross 1 million | I146: =IF(D146>=10,"sold more than 10 stores","did not sold more then 10 stores") -> sold more than 10 stores | J146: =IF(AND(G146 = "Electronics",AVERAGE(E146:E149)>4.5),"high rating Product","Average rating Product") -> Average rating Product | K146: =IF(AND(G146 = "Furniture",F146>5%),"long term use product","short term use product") -> short term use product
...

Sheet DATABASE FUNCTIONS
C3: 12 MODULE
C5: DATABASE FUNCTIONS | Y5: Points to be Noted
Y7: XLOOKUP , SORTING IS NOT AVAILABLE IN OLDER VERSION
C8: Question 1
D9: 1 | E9: 2 | F9: 3 | G9: 4 | H9: 5 | I9: 6 | J9: 7 | Y9: lookup
C10: Product ID | D10: Phone Names | E10: Category | F10: Price | G10: Stock | H10: Supplier | I10: Rating | J10: Discount | Y10: lookup help to find data from selected zone
C11: 101 | D11: iPhone 13 | E11: Smartphones | F11: 799 | G11: 120 | H11: John Smith | I11: 4.5 | J11: 0.05 | Y11: it always give data to last selected cell (column,row)
C12: 102 | D12: Galaxy S21 | E12: Smartphones | F12: 699 | G12: 85 | H12: Jane Doe | I12: 4 | J12: 0.1 | Y12: it always check the data of first column/row of selected cell to give result
C13: 103 | D13: Pixel 6 | E13: Smartphones | F13: 599 | G13: 60 | H13: Michael Johnson | I13: 4.7 | J13: 0
C14: 104 | D14: OnePlus 9 | E14: Smartphones | F14: 729 | G14: 150 | H14: Emily Davis | I14: 4.2 | J14: 0.15 | Y14: limitation
C15: 105 | D15: Redmi Note 10 | E15: Smartphones | F15: 199 | G15: 200 | H15: Chris Brown | I15: 4.8 | J15: 0.2 | Y15: if the value came above the desire value , it give its previous value of data
C16: 106 | D16: Moto G Power | E16: Smartphones | F16: 249 | G16: 100 | H16: Sarah Wilson | I16: 4.3 | J16: 0.05
C17: 107 | D17: Xperia 5 III | E17: Smartphones | F17: 899 | G17: 130 | H17: Daniel Martinez | I17: 4.1 | J17: 0.1 | Y17: solution
C18: 108 | D18: Nokia 8.3 | E18: Smartphones | F18: 479 | G18: 75 | H18: Laura White | I18: 4.4 | J18: 0.07 | Y18: data should always in ascending or correct form to get right result
C19: 109 | D19: LG Velvet | E19: Smartphones | F19: 599 | G19: 80 | H19: Robert Harris | I19: 4 | J19: 0.12
C20: 110 | D20: Huawei P30 | E20: Smartphones | F20: 649 | G20: 110 | H20: Jessica Clark | I20: 4.5 | J20: 0.08 | Y20: Vlookup - Vertical lookup (|)
C21: 111 | D21: ZTE Axon 20 | E21: Smartphones | F21: 399 | G21: 90 | H21: David Lewis | I21: 4.2 | J21: 0.06 | Y21: Hlookup - Horizontal lookup (-----)
C22: 112 | D22: HTC U12+ | E22: Smartphones | F22: 599 | G22: 60 | H22: Angela Robinson | I22: 4.1 | J22: 0.1 | Y22: 0 - Exact value ( if data did not have that value it give us error)
C23: 113 | D23: Oppo Find X3 | E23: Smartphones | F23: 799 | G23: 95 | H23: Thomas Walker | I23: 4.3 | J23: 0.04 | Y23: 1- approx value ( it give us previous data value that is smaller than our desired value)
C24: 114 | D24: Vivo X60 | E24: Smartphones | F24: 699 | G24: 140 | H24: Amy Hall | I24: 4.6 | J24: 0.03
C25: 115 | D25: Asus ROG Phone 5 | E25: Smartphones | F25: 999 | G25: 50 | H25: Steven Allen | I25: 4.8 | J25: 0 | Y25: Xlookup ( most useful and smartest lookup available in 2021 version)
C26: 116 | D26: Realme GT | E26: Smartphones | F26: 399 | G26: 120 | H26: Ashley Young | I26: 4.2 | J26: 0.05
C27: 117 | D27: Honor 50 | E27: Smartphones | F27: 549 | G27: 105 | H27: Brian King | I27: 4 | J27: 0.07 | Y27: INDEX and MATCH
C28: 118 | D28: BlackBerry Key2 | E28: Smartphones | F28: 699 | G28: 45 | H28: Karen Wright | I28: 4.7 | J28: 0.05 | Y28: Index function help to get the desire data from selected array
C29: 119 | D29: Fairphone 3+ | E29: Smartphones | F29: 469 | G29: 130 | H29: Edward Scott | I29: 4.4 | J29: 0.02 | Y29: Match function help to find the position of desired data
C30: 120 | D30: Palm Phone | E30: Smartphones | F30: 349 | G30: 60 | H30: Lisa Adams | I30: 4.5 | J30: 0.15
C32: VLOOKUP Questions
C34: 1. Using the above dataset, find the price of the iPhone 13 using the VLOOKUP function
C35: 2. Find the stock available for the Pixel 6 using the VLOOKUP function.
C36: 3. Determine the supplier for the Galaxy S21 using the VLOOKUP function.
C37: 4. Find the discount percentage for the Redmi Note 10 using the VLOOKUP function.
C38: 5. Retrieve the rating for the OnePlus 9 using the VLOOKUP function.
C39: 6. Find the price of the Nokia 8.3 using the VLOOKUP function.
C40: 7. Determine the supplier for the Xperia 5 III using the VLOOKUP function.
C41: 8. Retrieve the stock available for the LG Velvet using the VLOOKUP function.
C42: 9. Find the rating for the Oppo Find X3 using the VLOOKUP function.
C43: 10. Determine the discount for the Moto G Power using the VLOOKUP function.
B46: 1 | C46: Product ID | D46: 101 | E46: 102 | F46: 103 | G46: 104 | H46: 105 | I46: 106 | J46: 107 | K46: 108 | L46: 109 | M46: 110 | N46: 111 | O46: 112 | P46: 113 | Q46: 114 | R46: 115 | S46: 116 | T46: 117 | U46: 118 | V46: 119 | W46: 120
B47: 2 | C47: Phone Names | D47: iPhone 13 | E47: Galaxy S21 | F47: Pixel 6 | G47: OnePlus 9 | H47: Redmi Note 10 | I47: Moto G Power | J47: Xperia 5 III | K47: Nokia 8.3 | L47: LG Velvet | M47: Huawei P30 | N47: ZTE Axon 20 | O47: HTC U12+ | P47: Oppo Find X3 | Q47: Vivo X60 | R47: Asus ROG Phone 5 | S47: Realme GT | T47: Honor 50 | U47: BlackBerry Key2 | V47: Fairphone 3+ | W47: Palm Phone
B48: 3 | C48: Category | D48: Smartphones | E48: Smartphones | F48: Smartphones | G48: Smartphones | H48: Smartphones | I48: Smartphones | J48: Smartphones | K48: Smartphones | L48: Smartphones | M48: Smartphones | N48: Smartphones | O48: Smartphones | P48: Smartphones | Q48: Smartphones | R48: Smartphones | S48: Smartphones | T48: Smartphones | U48: Smartphones | V48: Smartphones | W48: Smartphones
B49: 4 | C49: Price | D49: 799 | E49: 699 | F49: 599 | G49: 729 | H49: 199 | I49: 249 | J49: 899 | K49: 479 | L49: 599 | M49: 649 | N49: 399 | O49: 599 | P49: 799 | Q49: 699 | R49: 999 | S49: 399 | T49: 549 | U49: 699 | V49: 469 | W49: 349
B50: 5 | C50: Stock | D50: 120 | E50: 85 | F50: 60 | G50: 150 | H50: 200 | I50: 100 | J50: 130 | K50: 75 | L50: 80 | M50: 110 | N50: 90 | O50: 60 | P50: 95 | Q50: 140 | R50: 50 | S50: 120 | T50: 105 | U50: 45 | V50: 130 | W50: 60
B51: 6 | C51: Supplier | D51: John Smith | E51: Jane Doe | F51: Michael Johnson | G51: Emily Davis | H51: Chris Brown | I51: Sarah Wilson | J51: Daniel Martinez | K51: Laura White | L51: Robert Harris | M51: Jessica Clark | N51: David Lewis | O51: Angela Robinson | P51: Thomas Walker | Q51: Amy Hall | R51: Steven Allen | S51: Ashley Young | T51: Brian King | U51: Karen Wright | V51: Edward Scott | W51: Lisa Adams
B52: 7 | C52: Rating | D52: 4.5 | E52: 4 | F52: 4.7 | G52: 4.2 | H52: 4.8 | I52: 4.3 | J52: 4.1 | K52: 4.4 | L52: 4 | M52: 4.5 | N52: 4.2 | O52: 4.1 | P52: 4.3 | Q52: 4.6 | R52: 4.8 | S52: 4.2 | T52: 4 | U52: 4.7 | V52: 4.4 | W52: 4.5
B53: 8 | C53: Discount | D53: 0.05 | E53: 0.1 | F53: 0 | G53: 0.15 | H53: 0.2 | I53: 0.05 | J53: 0.1 | K53: 0.07 | L53: 0.12 | M53: 0.08 | N53: 0.06 | O53: 0.1 | P53: 0.04 | Q53: 0.03 | R53: 0 | S53: 0.05 | T53: 0.07 | U53: 0.05 | V53: 0.02 | W53: 0.15
C56: HLOOKUP Questions
C58: 1. Using the above dataset, find the phone name with a Product ID of 106 .
C59: 2. Determine the category of the phone with a Product ID of 112 .
C60: 3. Find the price of the phone with a Product ID of 118 .
C61: 4. Retrieve the stock available for the phone with a Product ID of 110 .
C62: 5. Find the supplier for the phone with a Product ID of 109 .
C63: 6. Determine the rating of the phone with a Product ID of 105 .
C64: 7. Retrieve the discount for the phone with a Product ID of 116 .
C65: 8. Find the price of the phone with a Product ID of 114 .
C66: 9. Determine the supplier for the phone with a Product ID of 119 .
C67: 10. Retrieve the stock available for the phone with a Product ID of 108
C69: Solutions
C71: Vlookup Answers
C73: Question | D73: function | E73: formulas
C74: iphone 13 | D74: =VLOOKUP(C74,$D$11:$J$30,3,0) -> 799 | E74: =_xlfn.FORMULATEXT(D74) -> =VLOOKUP(C74,$D$11:$J$30,3,0)
C75: pixel 6 | D75: =VLOOKUP(C75,$D$11:$J$30,4,0) -> 60 | E75: =_xlfn.FORMULATEXT(D75) -> =VLOOKUP(C75,$D$11:$J$30,4,0)
C76: Galaxy S21 | D76: =VLOOKUP(C76,$D$11:$J$30,5,0) -> Jane Doe | E76: =_xlfn.FORMULATEXT(D76) -> =VLOOKUP(C76,$D$11:$J$30,5,0)
C77: redmi note 10 | D77: =VLOOKUP(C77,$D$11:$J$30,7,0) -> 0.2 | E77: =_xlfn.FORMULATEXT(D77) -> =VLOOKUP(C77,$D$11:$J$30,7,0)
C78: oneplus 9 | D78: =VLOOKUP(C78,$D$11:$J$30,6,0) -> 4.2 | E78: =_xlfn.FORMULATEXT(D78) -> =VLOOKUP(C78,$D$11:$J$30,6,0)
C79: nokia 8.3 | D79: =VLOOKUP(C79,$D$11:$J$30,3,0) -> 479 | E79: =_xlfn.FORMULATEXT(D79) -> =VLOOKUP(C79,$D$11:$J$30,3,0)
C80: xperia 5 III | D80: =VLOOKUP(C80,$D$11:$J$30,5,0) -> Daniel Martinez | E80: =_xlfn.FORMULATEXT(D80) -> =VLOOKUP(C80,$D$11:$J$30,5,0)
C81: LG Velvet | D81: =VLOOKUP(C81,$D$11:$J$30,4,0) -> 80 | E81: =_xlfn.FORMULATEXT(D81) -> =VLOOKUP(C81,$D$11:$J$30,4,0)
C82: Oppo find X3 | D82: =VLOOKUP(C82,$D$11:$J$30,6,0) -> 4.3 | E82: =_xlfn.FORMULATEXT(D82) -> =VLOOKUP(C82,$D$11:$J$30,6,0)
C83: Moto G Power | D83: =VLOOKUP(C83,$D$11:$J$30,7,0) -> 0.05 | E83: =_xlfn.FORMULATEXT(D83) -> =VLOOKUP(C83,$D$11:$J$30,7,0)
C86: Hlookup Answers
C88: Question | D88: function | E88: formulas
C89: 106 | D89: =HLOOKUP(C89,$D$46:$W$53,2,0) -> Moto G Power | E89: =_xlfn.FORMULATEXT(D89) -> =HLOOKUP(C89,$D$46:$W$53,2,0)
C90: 112 | D90: =HLOOKUP(C90,$D$46:$W$53,3,0) -> Smartphones | E90: =_xlfn.FORMULATEXT(D90) -> =HLOOKUP(C90,$D$46:$W$53,3,0)
C91: 118 | D91: =HLOOKUP(C91,$D$46:$W$53,4,0) -> 699 | E91: =_xlfn.FORMULATEXT(D91) -> =HLOOKUP(C91,$D$46:$W$53,4,0)
C92: 110 | D92: =HLOOKUP(C92,$D$46:$W$53,5,0) -> 110 | E92: =_xlfn.FORMULATEXT(D92) -> =HLOOKUP(C92,$D$46:$W$53,5,0)
C93: 109 | D93: =HLOOKUP(C93,$D$46:$W$53,6,0) -> Robert Harris | E93: =_xlfn.FORMULATEXT(D93) -> =HLOOKUP(C93,$D$46:$W$53,6,0)
C94: 105 | D94: =HLOOKUP(C94,$D$46:$W$53,7,0) -> 4.8 | E94: =_xlfn.FORMULATEXT(D94) -> =HLOOKUP(C94,$D$46:$W$53,7,0)
C95: 116 | D95: =HLOOKUP(C95,$D$46:$W$53,8,0) -> 0.05 | E95: =_xlfn.FORMULATEXT(D95) -> =HLOOKUP(C95,$D$46:$W$53,8,0)
C96: 114 | D96: =HLOOKUP(C96,$D$46:$W$53,4,0) -> 699 | E96: =_xlfn.FORMULATEXT(D96) -> =HLOOKUP(C96,$D$46:$W$53,4,0)
C97: 119 | D97: =HLOOKUP(C97,$D$46:$W$53,6,0) -> Edward Scott | E97: =_xlfn.FORMULATEXT(D97) -> =HLOOKUP(C97,$D$46:$W$53,6,0)
C98: 108 | D98: =HLOOKUP(C98,$D$46:$W$53,5,0) -> 75 | E98: =_xlfn.FORMULATEXT(D98) -> =HLOOKUP(C98,$D$46:$W$53,5,0)
C101: Question 2
C103: Suppose you have a dataset with sales data for different products across various regions and quarters. You need to create a formula that can retrieve the sales figure for a specific product, region, and quarter.
C105: Data Layout:
E107: Sheet1 (Sales Data):
C109: Region | D109: Product | E109: Q1 2023 | F109: Q2 2023 | G109: Q3 2023 | H109: Q4 2023
C110: North | D110: Apple | E110: 1500 | F110: 1600 | G110: 1700 | H110: 1800
C111: North | D111: Redmi | E111: 1400 | F111: 1500 | G111: 1600 | H111: 1700
C112: South | D112: Apple | E112: 1200 | F112: 1300 | G112: 1400 | H112: 1500
C113: South | D113: Redmi | E113: 1100 | F113: 1200 | G113: 1300 | H113: 1400
E115: Sheet2 (Criteria):
E117: Criteria | F117: Value
E118: Region | F118: North
E119: Product | F119: Apple
E120: Quarter | F120: Q3 2023
C123: Solutions
C125: Region | D125: Product | E125: Quartly | F125: Result | G125: formula
C126: South | D126: Apple | E126: Q2 2023 | F126: =INDEX(E110:H113,MATCH(C126,C110:C113, 0)+( MATCH(D126,D110:D113, 0)-1), MATCH(E126,E109:H109, 0)) -> 1300 | G126: =_xlfn.FORMULATEXT(F126) -> =@INDEX(E110:H113,MATCH(C126,C110:C113, 0)+( MATCH(D126,D110:D113, 0)-1), MATCH(E126,E109:H109, 0))
C129: Question 3
C132: You work for a company that tracks the sales performance of various supercars across different regions. You have a table that lists the sales data for each supercar model in different regions, as well as another table that lists the target sales for each model in each region.
...

Sheet FUNCTIONS PRACTICE
B2: Question 1
B4: Questions: | K4: Answer
K5: 1 | L5: product Id | M5: =LOOKUP("00000014",B31:B72,L31:L72) -> Karen N. Harris
B6: 1. Text Extraction: | L6: "00000014" | M6: =LEFT(M5,FIND(" ",M5)) -> Karen
B7: Extract the first and last name from the Supplier Name column for the product with Product ID "00000014". | M7: =TRIM(RIGHT(M5,LEN(M5)-(FIND(" ",M5)+1)-1)) -> Harris
B8: 2. Date and Time Formatting:
B9: Display the current date and time in the formats "MM/DD/YYYY" and "HH:MM | K9: 2 | L9: current day and time | M9: format mm/dd/yyyy
B10: " respectively. | L10: =NOW() -> 45722.797 | M10: =(TEXT(L10,"mm dd yyyy")) -> 03 06 2025
B11: 3. Sales Analysis:
B12: Calculate the total, average, minimum, and maximum sales amounts. | K12: 3 | L12: total | M12: =SUM('FUNCTIONS PRACTICE'!$E$31:$E$72) -> 36650
B13: Determine the number of products with a sales amount greater than $1000. | L13: average | M13: =AVERAGE('FUNCTIONS PRACTICE'!$E$31:$E$72) -> 872.61905
B14: Count the number of products with a rating of 5. | L14: min | M14: =MIN('FUNCTIONS PRACTICE'!$E$31:$E$72) -> 300
B15: 4. Lookup: | L15: max | M15: =MAX('FUNCTIONS PRACTICE'!$E$31:$E$72) -> 1800
B16: Find the sales amount for the product with Product ID "00000018".
B17: 5. Categorization: | L17: no of products | M17: =COUNTIF(E31:E72,">=1000") -> 15
B18: Create a new column that categorizes products as "High Discount" if the discount is greater than 15% and "Low Discount" otherwise. | L18: no of products, rating 5 | M18: =COUNTIF(I31:I72,">=5") -> 20
B19: 6. Text Manipulation:
B20: Convert the product names to uppercase, lowercase, and proper case. | K20: 4 | L20: sales amount | M20: =VLOOKUP("00000018",B31:AA72,4,0) -> 500
B21: 7. Length and Replacement:
B22: Find the length of the product name for the product with Product ID "00000025". | K22: 7 | L22: len
B23: Modify customer feedback to standardize phrases, such as replacing "Good" with "Excellent". | L23: "00000025" | M23: =LEN(INDEX(C31:C72,MATCH("00000025",B31:B72,0),)) -> 11
B24: 8. Additional Tasks:
B25: Calculate the total sales for all products in the West region. | K25: 8 | L25: total sales in west region | M25: =SUMIF(B31:V72,LOOKUP("west",J31:J71,E31:E72)) -> 3500
B26: Format the sales date of the product with Product ID "00000027" in "DD-MMM-YYYY" format. | L26: =LOOKUP("00000027",B31:B72,G31:G72) -> 03/14/2023 | M26: =TEXT(L26,"mmm dd yyyy") -> 03/14/2023
X29: Ans 6 | AA29: Ans 5
B30: Product ID | C30: Product Name | D30: Category | E30: Sales Amount ($) | F30: Number of Units Sold | G30: Sales Date | H30: Customer Feedback | I30: Rating | J30: Region | K30: Discount (%) | L30: Supplier Name | M30: Warranty Period (months) | N30: Return Rate (%) | O30: Customer DOB | P30: Sales Channel | Q30: Inventory Level | R30: Shipping Cost ($) | S30: Payment Method | T30: Store Location | U30: Marketing Spend ($) | V30: Promotion Used | X30: upper case(P) | Y30: Lower case(P) | Z30: Proper case(P) | AA30: Discount
B31: 00000001 | C31: iPhone 13 Pro | D31: Electronics | E31: 1200 | F31: 50 | G31: 01/15/2023 | H31: Excellent product | I31: 5 | J31: East | K31: 10 | L31: John A. Smith | M31: 12 | N31: 2 | O31: 32640 | P31: Online | Q31: High | R31: 20 | S31: Credit Card | T31: New York | U31: 2000 | V31: Black Friday | X31: =UPPER(C31) -> IPHONE 13 PRO | Y31: =LOWER(X31) -> iphone 13 pro | Z31: =PROPER(Y31) -> Iphone 13 Pro | AA31: =IF(K31>=0.15*100,"High Discount","Low Discount") -> Low Discount
B32: 00000002 | C32: OnePlus 8T | D32: Electronics | E32: 950 | F32: 25 | G32: 01/30/2023 | H32: Fast and smooth | I32: 5 | J32: North | K32: 15 | L32: Richard T. Wright | M32: 18 | N32: 1 | O32: 34515 | P32: Online | Q32: Medium | R32: 20 | S32: Debit Card | T32: Washington | U32: 1100 | V32: Holiday Sale | X32: =UPPER(C32) -> ONEPLUS 8T | Y32: =LOWER(X32) -> oneplus 8t | Z32: =PROPER(Y32) -> Oneplus 8T | AA32: =IF(K32>=0.15*100,"High Discount","Low Discount") -> High Discount
B33: 00000003 | C33: Google Pixel 6 | D33: Electronics | E33: 900 | F33: 30 | G33: 45049 | H33: Good performance | I33: 4 | J33: North | K33: 15 | L33: James C. Williams | M33: 18 | N33: 3 | O33: 33793 | P33: Online | Q33: Low | R33: 15 | S33: Credit Card | T33: Chicago | U33: 1000 | V33: New Year Sale | X33: =UPPER(C33) -> GOOGLE PIXEL 6 | Y33: =LOWER(X33) -> google pixel 6 | Z33: =PROPER(Y33) -> Google Pixel 6 | AA33: =IF(K33>=0.15*100,"High Discount","Low Discount") -> High Discount
B34: 00000004 | C34: OnePlus 9 | D34: Electronics | E34: 750 | F34: 60 | G34: 01/20/2023 | H34: Excellent value | I34: 5 | J34: South | K34: 20 | L34: Patricia D. Brown | M34: 12 | N34: 4 | O34: 31092 | P34: In-Store | Q34: High | R34: 10 | S34: Debit Card | T34: Miami | U34: 800 | V34: End of Season Sale | X34: =UPPER(C34) -> ONEPLUS 9 | Y34: =LOWER(X34) -> oneplus 9 | Z34: =PROPER(Y34) -> Oneplus 9 | AA34: =IF(K34>=0.15*100,"High Discount","Low Discount") -> High Discount
B35: 00000005 | C35: Sony Xperia 5 | D35: Electronics | E35: 600 | F35: 55 | G35: 45262 | H35: Great display and performance | I35: 4 | J35: East | K35: 10 | L35: Aaron M. Lewis | M35: 12 | N35: 3 | O35: 32673 | P35: Online | Q35: Medium | R35: 20 | S35: Credit Card | T35: New York | U35: 850 | V35: Holiday Sale | X35: =UPPER(C35) -> SONY XPERIA 5 | Y35: =LOWER(X35) -> sony xperia 5 | Z35: =PROPER(Y35) -> Sony Xperia 5 | AA35: =IF(K35>=0.15*100,"High Discount","Low Discount") -> Low Discount
B36: 00000006 | C36: Samsung Galaxy S21 | D36: Electronics | E36: 1000 | F36: 45 | G36: 01/18/2023 | H36: Excellent screen quality | I36: 5 | J36: South | K36: 15 | L36: Julie M. Taylor | M36: 18 | N36: 2 | O36: 34689 | P36: In-Store | Q36: Medium | R36: 15 | S36: Debit Card | T36: Miami | U36: 1200 | V36: Flash Sale | X36: =UPPER(C36) -> SAMSUNG GALAXY S21 | Y36: =LOWER(X36) -> samsung galaxy s21 | Z36: =PROPER(Y36) -> Samsung Galaxy S21 | AA36: =IF(K36>=0.15*100,"High Discount","Low Discount") -> High Discount
B37: 00000006 | C37: Samsung Galaxy S21 | D37: Electronics | E37: 1000 | F37: 45 | G37: 01/18/2023 | H37: Excellent screen quality | I37: 5 | J37: South | K37: 15 | L37: Julie M. Taylor | M37: 18 | N37: 2 | O37: 34689 | P37: In-Store | Q37: Medium | R37: 15 | S37: Debit Card | T37: Miami | U37: 1200 | V37: Flash Sale | X37: =UPPER(C37) -> SAMSUNG GALAXY S21 | Y37: =LOWER(X37) -> samsung galaxy s21 | Z37: =PROPER(Y37) -> Samsung Galaxy S21 | AA37: =IF(K37>=0.15*100,"High Discount","Low Discount") -> High Discount
B38: 00000007 | C38: LG V60 ThinQ | D38: Electronics | E38: 950 | F38: 30 | G38: 44929 | H38: Great dual screen | I38: 4 | J38: North | K38: 5 | L38: Steven J. Lee | M38: 12 | N38: 2 | O38: 33428 | P38: Online | Q38: Medium | R38: 10 | S38: PayPal | T38: Chicago | U38: 1100 | V38: Spring Sale | X38: =UPPER(C38) -> LG V60 THINQ | Y38: =LOWER(X38) -> lg v60 thinq | Z38: =PROPER(Y38) -> Lg V60 Thinq | AA38: =IF(K38>=0.15*100,"High Discount","Low Discount") -> Low Discount
B39: 00000008 | C39: Nokia 8.3 | D39: Electronics | E39: 450 | F39: 50 | G39: 45201 | H39: Decent performance | I39: 3 | J39: South | K39: 5 | L39: Barbara H. Wilson | M39: 12 | N39: 4 | O39: 34197 | P39: In-Store | Q39: Medium | R39: 15 | S39: Debit Card | T39: Miami | U39: 500 | V39: Winter Sale | X39: =UPPER(C39) -> NOKIA 8.3 | Y39: =LOWER(X39) -> nokia 8.3 | Z39: =PROPER(Y39) -> Nokia 8.3 | AA39: =IF(K39>=0.15*100,"High Discount","Low Discount") -> Low Discount
B40: 00000009 | C40: Realme 8 Pro | D40: Electronics | E40: 700 | F40: 40 | G40: 02/15/2023 | H40: Good performance | I40: 4 | J40: West | K40: 20 | L40: Tina G. White | M40: 18 | N40: 3 | O40: 33716 | P40: In-Store | Q40: Low | R40: 25 | S40: Debit Card | T40: San Francisco | U40: 800 | V40: Winter Sale | X40: =UPPER(C40) -> REALME 8 PRO | Y40: =LOWER(X40) -> realme 8 pro | Z40: =PROPER(Y40) -> Realme 8 Pro | AA40: =IF(K40>=0.15*100,"High Discount","Low Discount") -> High Discount
B41: 00000010 | C41: Xiaomi Mi 11 | D41: Electronics | E41: 850 | F41: 40 | G41: 01/25/2023 | H41: Affordable and reliable | I41: 4 | J41: West | K41: 20 | L41: Elizabeth J. Taylor | M41: 24 | N41: 3 | O41: 35241 | P41: In-Store | Q41: Medium | R41: 25 | S41: PayPal | T41: Los Angeles | U41: 1200 | V41: Flash Sale | X41: =UPPER(C41) -> XIAOMI MI 11 | Y41: =LOWER(X41) -> xiaomi mi 11 | Z41: =PROPER(Y41) -> Xiaomi Mi 11 | AA41: =IF(K41>=0.15*100,"High Discount","Low Discount") -> High Discount
B42: 00000011 | C42: Xiaomi Mi Note 10 | D42: Electronics | E42: 700 | F42: 45 | G42: 03/18/2023 | H42: Good value for the price | I42: 4 | J42: South | K42: 15 | L42: Marcus J. Hall | M42: 12 | N42: 3 | O42: 32385 | P42: In-Store | Q42: High | R42: 15 | S42: PayPal | T42: Miami | U42: 900 | V42: Black Friday | X42: =UPPER(C42) -> XIAOMI MI NOTE 10 | Y42: =LOWER(X42) -> xiaomi mi note 10 | Z42: =PROPER(Y42) -> Xiaomi Mi Note 10 | AA42: =IF(K42>=0.15*100,"High Discount","Low Discount") -> High Discount
B43: 00000012 | C43: iPhone 12 Mini | D43: Electronics | E43: 1000 | F43: 45 | G43: 45263 | H43: Good performance | I43: 4 | J43: South | K43: 10 | L43: Sarah L. Jackson | M43: 12 | N43: 2 | O43: 34296 | P43: Online | Q43: Medium | R43: 20 | S43: PayPal | T43: Seattle | U43: 1100 | V43: End of Season Sale | X43: =UPPER(C43) -> IPHONE 12 MINI | Y43: =LOWER(X43) -> iphone 12 mini | Z43: =PROPER(Y43) -> Iphone 12 Mini | AA43: =IF(K43>=0.15*100,"High Discount","Low Discount") -> Low Discount
B44: 00000013 | C44: Xiaomi Mi Mix 4 | D44: Electronics | E44: 850 | F44: 45 | G44: 44928 | H44: Great display | I44: 4 | J44: North | K44: 10 | L44: Samuel W. Baker | M44: 12 | N44: 2 | O44: 32947 | P44: Online | Q44: Medium | R44: 20 | S44: PayPal | T44: Seattle | U44: 1000 | V44: Winter Sale | X44: =UPPER(C44) -> XIAOMI MI MIX 4 | Y44: =LOWER(X44) -> xiaomi mi mix 4 | Z44: =PROPER(Y44) -> Xiaomi Mi Mix 4 | AA44: =IF(K44>=0.15*100,"High Discount","Low Discount") -> Low Discount
B45: 00000014 | C45: Google Pixel 5 | D45: Electronics | E45: 750 | F45: 55 | G45: 01/29/2023 | H45: Great camera | I45: 5 | J45: West | K45: 15 | L45: Karen N. Harris | M45: 24 | N45: 3 | O45: 35469 | P45: Online | Q45: Low | R45: 10 | S45: Debit Card | T45: San Francisco | U45: 950 | V45: Spring Sale | X45: =UPPER(C45) -> GOOGLE PIXEL 5 | Y45: =LOWER(X45) -> google pixel 5 | Z45: =PROPER(Y45) -> Google Pixel 5 | AA45: =IF(K45>=0.15*100,"High Discount","Low Discount") -> High Discount
B46: 00000015 | C46: Apple iPhone 13 | D46: Electronics | E46: 1300 | F46: 30 | G46: 45263 | H46: Excellent performance | I46: 5 | J46: South | K46: 10 | L46: Patricia M. Clark | M46: 24 | N46: 2 | O46: 32486 | P46: In-Store | Q46: High | R46: 15 | S46: Credit Card | T46: Miami | U46: 1400 | V46: Spring Sale | X46: =UPPER(C46) -> APPLE IPHONE 13 | Y46: =LOWER(X46) -> apple iphone 13 | Z46: =PROPER(Y46) -> Apple Iphone 13 | AA46: =IF(K46>=0.15*100,"High Discount","Low Discount") -> Low Discount
B47: 00000016 | C47: Motorola Razr | D47: Electronics | E47: 1200 | F47: 30 | G47: 01/14/2023 | H47: Nostalgic design | I47: 4 | J47: South | K47: 5 | L47: Betty P. Johnson | M47: 18 | N47: 2 | O47: 32389 | P47: Online | Q47: Medium | R47: 20 | S47: Debit Card | T47: Miami | U47: 1000 | V47: Black Friday | X47: =UPPER(C47) -> MOTOROLA RAZR | Y47: =LOWER(X47) -> motorola razr | Z47: =PROPER(Y47) -> Motorola Razr | AA47: =IF(K47>=0.15*100,"High Discount","Low Discount") -> Low Discount
B48: 00000017 | C48: Sony Xperia 1 | D48: Electronics | E48: 950 | F48: 40 | G48: 02/20/2023 | H48: High-quality display | I48: 5 | J48: East | K48: 15 | L48: Steven Q. Young | M48: 24 | N48: 2 | O48: 31158 | P48: In-Store | Q48: Low | R48: 10 | S48: Debit Card | T48: Phoenix | U48: 1250 | V48: Flash Sale | X48: =UPPER(C48) -> SONY XPERIA 1 | Y48: =LOWER(X48) -> sony xperia 1 | Z48: =PROPER(Y48) -> Sony Xperia 1 | AA48: =IF(K48>=0.15*100,"High Discount","Low Discount") -> High Discount
B49: 00000018 | C49: LG Wing | D49: Electronics | E49: 500 | F49: 60 | G49: 45141 | H49: Innovative but bulky | I49: 3 | J49: West | K49: 20 | L49: Donna R. Allen | M49: 18 | N49: 3 | O49: 32795 | P49: Online | Q49: Medium | R49: 25 | S49: PayPal | T49: Dallas | U49: 900 | V49: End of Season Sale | X49: =UPPER(C49) -> LG WING | Y49: =LOWER(X49) -> lg wing | Z49: =PROPER(Y49) -> Lg Wing | AA49: =IF(K49>=0.15*100,"High Discount","Low Discount") -> High Discount
B50: 00000019 | C50: Apple iPhone 11 Pro | D50: Electronics | E50: 1300 | F50: 20 | G50: 45110 | H50: Excellent camera | I50: 5 | J50: West | K50: 15 | L50: Jessica L. Garcia | M50: 18 | N50: 2 | O50: 31725 | P50: In-Store | Q50: Low | R50: 25 | S50: PayPal | T50: San Francisco | U50: 1600 | V50: Spring Sale | X50: =UPPER(C50) -> APPLE IPHONE 11 PRO | Y50: =LOWER(X50) -> apple iphone 11 pro | Z50: =PROPER(Y50) -> Apple Iphone 11 Pro | AA50: =IF(K50>=0.15*100,"High Discount","Low Discount") -> High Discount
B51: 00000020 | C51: Apple iPhone SE | D51: Electronics | E51: 400 | F51: 90 | G51: 45049 | H51: Exceeds expectations | I51: 5 | J51: East | K51: 10 | L51: William I. Moore | M51: 6 | N51: 1 | O51: 33307 | P51: Online | Q51: High | R51: 20 | S51: Credit Card | T51: New York | U51: 900 | V51: Holiday Sale | X51: =UPPER(C51) -> APPLE IPHONE SE | Y51: =LOWER(X51) -> apple iphone se | Z51: =PROPER(Y51) -> Apple Iphone Se | AA51: =IF(K51>=0.15*100,"High Discount","Low Discount") -> Low Discount
B52: 00000021 | C52: Xiaomi Poco X3 | D52: Electronics | E52: 650 | F52: 45 | G52: 03/18/2023 | H52: Great battery life | I52: 4 | J52: East | K52: 10 | L52: Brian U. King | M52: 18 | N52: 3 | O52: 33108 | P52: Online | Q52: Medium | R52: 20 | S52: Credit Card | T52: New York | U52: 1200 | V52: Spring Sale | X52: =UPPER(C52) -> XIAOMI POCO X3 | Y52: =LOWER(X52) -> xiaomi poco x3 | Z52: =PROPER(Y52) -> Xiaomi Poco X3 | AA52: =IF(K52>=0.15*100,"High Discount","Low Discount") -> Low Discount
B53: 00000022 | C53: Huawei Mate 40 | D53: Electronics | E53: 1100 | F53: 25 | G53: 01/27/2023 | H53: Excellent camera | I53: 5 | J53: West | K53: 15 | L53: Cynthia V. Martinez | M53: 24 | N53: 1 | O53: 32281 | P53: In-Store | Q53: High | R53: 25 | S53: Debit Card | T53: Los Angeles | U53: 1500 | V53: Summer Sale | X53: =UPPER(C53) -> HUAWEI MATE 40 | Y53: =LOWER(X53) -> huawei mate 40 | Z53: =PROPER(Y53) -> Huawei Mate 40 | AA53: =IF(K53>=0.15*100,"High Discount","Low Discount") -> High Discount
B54: 00000023 | C54: Oppo Find X2 | D54: Electronics | E54: 700 | F54: 40 | G54: 02/22/2023 | H54: Decent performance | I54: 3 | J54: North | K54: 5 | L54: Timothy W. Hernandez | M54: 12 | N54: 4 | O54: 34650 | P54: Online | Q54: Low | R54: 10 | S54: PayPal | T54: Chicago | U54: 800 | V54: Winter Sale | X54: =UPPER(C54) -> OPPO FIND X2 | Y54: =LOWER(X54) -> oppo find x2 | Z54: =PROPER(Y54) -> Oppo Find X2 | AA54: =IF(K54>=0.15*100,"High Discount","Low Discount") -> Low Discount
B55: 00000024 | C55: Vivo V21 | D55: Electronics | E55: 850 | F55: 35 | G55: 03/29/2023 | H55: Good value for money | I55: 4 | J55: South | K55: 20 | L55: Angela X. Robinson | M55: 6 | N55: 2 | O55: 33496 | P55: In-Store | Q55: Medium | R55: 15 | S55: Credit Card | T55: Miami | U55: 1000 | V55: End of Season Sale | X55: =UPPER(C55) -> VIVO V21 | Y55: =LOWER(X55) -> vivo v21 | Z55: =PROPER(Y55) -> Vivo V21 | AA55: =IF(K55>=0.15*100,"High Discount","Low Discount") -> High Discount
B56: 00000025 | C56: ZTE Axon 20 | D56: Electronics | E56: 500 | F56: 50 | G56: 01/22/2023 | H56: Innovative design | I56: 4 | J56: East | K56: 10 | L56: Deborah Y. Thompson | M56: 12 | N56: 3 | O56: 31983 | P56: Online | Q56: High | R56: 20 | S56: Debit Card | T56: New York | U56: 900 | V56: Holiday Sale | X56: =UPPER(C56) -> ZTE AXON 20 | Y56: =LOWER(X56) -> zte axon 20 | Z56: =PROPER(Y56) -> Zte Axon 20 | AA56: =IF(K56>=0.15*100,"High Discount","Low Discount") -> Low Discount
B57: 00000026 | C57: Realme GT | D57: Electronics | E57: 900 | F57: 60 | G57: 45048 | H57: Fast and reliable | I57: 5 | J57: West | K57: 10 | L57: Edward Z. Martinez | M57: 24 | N57: 2 | O57: 33647 | P57: In-Store | Q57: Medium | R57: 15 | S57: PayPal | T57: Los Angeles | U57: 1000 | V57: End of Season Sale | X57: =UPPER(C57) -> REALME GT | Y57: =LOWER(X57) -> realme gt | Z57: =PROPER(Y57) -> Realme Gt | AA57: =IF(K57>=0.15*100,"High Discount","Low Discount") -> Low Discount
B58: 00000026 | C58: Realme GT | D58: Electronics | E58: 900 | F58: 60 | G58: 45048 | H58: Fast and reliable | I58: 5 | J58: West | K58: 10 | L58: Edward Z. Martinez | M58: 24 | N58: 2 | O58: 33647 | P58: In-Store | Q58: Medium | R58: 15 | S58: PayPal | T58: Los Angeles | U58: 1000 | V58: End of Season Sale | X58: =UPPER(C58) -> REALME GT | Y58: =LOWER(X58) -> realme gt | Z58: =PROPER(Y58) -> Realme Gt | AA58: =IF(K58>=0.15*100,"High Discount","Low Discount") -> Low Discount
B59: 00000027 | C59: Asus ROG Phone 5 | D59: Electronics | E59: 1500 | F59: 20 | G59: 03/14/2023 | H59: Excellent for gaming | I59: 5 | J59: North | K59: 15 | L59: Frank A. Lewis | M59: 18 | N59: 1 | O59: 35053 | P59: Online | Q59: Low | R59: 10 | S59: Credit Card | T59: Chicago | U59: 1500 | V59: Cyber Monday | X59: =UPPER(C59) -> ASUS ROG PHONE 5 | Y59: =LOWER(X59) -> asus rog phone 5 | Z59: =PROPER(Y59) -> Asus Rog Phone 5 | AA59: =IF(K59>=0.15*100,"High Discount","Low Discount") -> High Discount
B60: 00000028 | C60: Lenovo Legion Duel | D60: Electronics | E60: 1300 | F60: 30 | G60: 45261 | H60: Powerful and sleek | I60: 5 | J60: South | K60: 5 | L60: Gina B. Walker | M60: 6 | N60: 2 | O60: 32786 | P60: In-Store | Q60: High | R60: 15 | S60: Debit Card | T60: Miami | U60: 1400 | V60: New Year Sale | X60: =UPPER(C60) -> LENOVO LEGION DUEL | Y60: =LOWER(X60) -> lenovo legion duel | Z60: =PROPER(Y60) -> Lenovo Legion Duel | AA60: =IF(K60>=0.15*100,"High Discount","Low Discount") -> Low Discount
B61: 00000029 | C61: Honor 50 | D61: Electronics | E61: 750 | F61: 50 | G61: 45110 | H61: Good camera | I61: 4 | J61: East | K61: 20 | L61: Howard C. Hall | M61: 24 | N61: 2 | O61: 32943 | P61: Online | Q61: Medium | R61: 20 | S61: PayPal | T61: New York | U61: 1000 | V61: Summer Sale | X61: =UPPER(C61) -> HONOR 50 | Y61: =LOWER(X61) -> honor 50 | Z61: =PROPER(Y61) -> Honor 50 | AA61: =IF(K61>=0.15*100,"High Discount","Low Discount") -> High Discount
B62: 00000030 | C62: Honor V40 | D62: Electronics | E62: 800 | F62: 35 | G62: 45261 | H62: Strong performance | I62: 4 | J62: East | K62: 10 | L62: Julia H. Lewis | M62: 24 | N62: 2 | O62: 32929 | P62: Online | Q62: Medium | R62: 20 | S62: Credit Card | T62: New York | U62: 1100 | V62: End of Season Sale | X62: =UPPER(C62) -> HONOR V40 | Y62: =LOWER(X62) -> honor v40 | Z62: =PROPER(Y62) -> Honor V40 | AA62: =IF(K62>=0.15*100,"High Discount","Low Discount") -> Low Discount
B63: 00000031 | C63: Apple iPhone 12 | D63: Electronics | E63: 1100 | F63: 40 | G63: 02/28/2023 | H63: Fast and sleek | I63: 5 | J63: North | K63: 15 | L63: Jason E. Young | M63: 18 | N63: 1 | O63: 34344 | P63: Online | Q63: Medium | R63: 10 | S63: Debit Card | T63: Chicago | U63: 1200 | V63: Fall Sale | X63: =UPPER(C63) -> APPLE IPHONE 12 | Y63: =LOWER(X63) -> apple iphone 12 | Z63: =PROPER(Y63) -> Apple Iphone 12 | AA63: =IF(K63>=0.15*100,"High Discount","Low Discount") -> High Discount
B64: 00000032 | C64: Samsung Galaxy Z Fold2 | D64: Electronics | E64: 1800 | F64: 15 | G64: 01/25/2023 | H64: Amazing foldable screen | I64: 5 | J64: South | K64: 5 | L64: Katherine F. Wright | M64: 6 | N64: 2 | O64: 33315 | P64: In-Store | Q64: High | R64: 15 | S64: PayPal | T64: Miami | U64: 2000 | V64: Winter Sale | X64: =UPPER(C64) -> SAMSUNG GALAXY Z FOLD2 | Y64: =LOWER(X64) -> samsung galaxy z fold2 | Z64: =PROPER(Y64) -> Samsung Galaxy Z Fold2 | AA64: =IF(K64>=0.15*100,"High Discount","Low Discount") -> Low Discount
B65: 00000033 | C65: Google Pixel 4a | D65: Electronics | E65: 400 | F65: 80 | G65: 03/23/2023 | H65: Compact and reliable | I65: 4 | J65: East | K65: 10 | L65: Larry G. King | M65: 24 | N65: 3 | O65: 31220 | P65: Online | Q65: Medium | R65: 20 | S65: Credit Card | T65: New York | U65: 900 | V65: Flash Sale | X65: =UPPER(C65) -> GOOGLE PIXEL 4A | Y65: =LOWER(X65) -> google pixel 4a | Z65: =PROPER(Y65) -> Google Pixel 4A | AA65: =IF(K65>=0.15*100,"High Discount","Low Discount") -> Low Discount
B66: 00000034 | C66: OnePlus Nord N10 | D66: Electronics | E66: 700 | F66: 70 | G66: 02/21/2023 | H66: Good value for money | I66: 4 | J66: West | K66: 20 | L66: Michelle H. Harris | M66: 12 | N66: 2 | O66: 33876 | P66: In-Store | Q66: High | R66: 25 | S66: Debit Card | T66: Los Angeles | U66: 1000 | V66: End of Season Sale | X66: =UPPER(C66) -> ONEPLUS NORD N10 | Y66: =LOWER(X66) -> oneplus nord n10 | Z66: =PROPER(Y66) -> Oneplus Nord N10 | AA66: =IF(K66>=0.15*100,"High Discount","Low Discount") -> High Discount
B67: 00000035 | C67: Motorola G Stylus | D67: Electronics | E67: 300 | F67: 90 | G67: 01/30/2023 | H67: Affordable and useful | I67: 4 | J67: North | K67: 5 | L67: Nathan I. Johnson | M67: 18 | N67: 4 | O67: 33224 | P67: Online | Q67: Medium | R67: 10 | S67: PayPal | T67: Chicago | U67: 700 | V67: Spring Sale | X67: =UPPER(C67) -> MOTOROLA G STYLUS | Y67: =LOWER(X67) -> motorola g stylus | Z67: =PROPER(Y67) -> Motorola G Stylus | AA67: =IF(K67>=0.15*100,"High Discount","Low Discount") -> Low Discount
B68: 00000037 | C68: Sony Xperia 10 II | D68: Electronics | E68: 600 | F68: 50 | G68: 45019 | H68: Decent mid-range phone | I68: 3 | J68: South | K68: 10 | L68: Olivia J. Martinez | M68: 24 | N68: 3 | O68: 34061 | P68: In-Store | Q68: High | R68: 15 | S68: Credit Card | T68: Miami | U68: 800 | V68: Summer Sale | X68: =UPPER(C68) -> SONY XPERIA 10 II | Y68: =LOWER(X68) -> sony xperia 10 ii | Z68: =PROPER(Y68) -> Sony Xperia 10 Ii | AA68: =IF(K68>=0.15*100,"High Discount","Low Discount") -> Low Discount
B69: 00000038 | C69: Nokia 5.3 | D69: Electronics | E69: 300 | F69: 100 | G69: 01/15/2023 | H69: Budget-friendly | I69: 3 | J69: West | K69: 10 | L69: Quincy L. Walker | M69: 12 | N69: 4 | O69: 35010 | P69: In-Store | Q69: High | R69: 25 | S69: PayPal | T69: Los Angeles | U69: 500 | V69: Holiday Sale | X69: =UPPER(C69) -> NOKIA 5.3 | Y69: =LOWER(X69) -> nokia 5.3 | Z69: =PROPER(Y69) -> Nokia 5.3 | AA69: =IF(K69>=0.15*100,"High Discount","Low Discount") -> Low Discount
B70: 00000039 | C70: Apple iPhone 11 | D70: Electronics | E70: 1200 | F70: 30 | G70: 02/18/2023 | H70: Excellent performance | I70: 5 | J70: North | K70: 20 | L70: Rachel M. Thompson | M70: 24 | N70: 1 | O70: 33251 | P70: Online | Q70: Medium | R70: 15 | S70: Credit Card | T70: Chicago | U70: 1500 | V70: Black Friday | X70: =UPPER(C70) -> APPLE IPHONE 11 | Y70: =LOWER(X70) -> apple iphone 11 | Z70: =PROPER(Y70) -> Apple Iphone 11 | AA70: =IF(K70>=0.15*100,"High Discount","Low Discount") -> High Discount
B71: 00000040 | C71: Samsung Galaxy Note 20 | D71: Electronics | E71: 1000 | F71: 35 | G71: 45049 | H71: Great for productivity | I71: 5 | J71: South | K71: 5 | L71: Matthew P. Thomas | M71: 24 | N71: 1 | O71: 32854 | P71: Online | Q71: Medium | R71: 20 | S71: Debit Card | T71: Miami | U71: 1100 | V71: Summer Sale | X71: =UPPER(C71) -> SAMSUNG GALAXY NOTE 20 | Y71: =LOWER(X71) -> samsung galaxy note 20 | Z71: =PROPER(Y71) -> Samsung Galaxy Note 20 | AA71: =IF(K71>=0.15*100,"High Discount","Low Discount") -> Low Discount
B72: 00000040 | C72: Samsung Galaxy Note 20 | D72: Electronics | E72: 1000 | F72: 35 | G72: 45049 | H72: Great for productivity | I72: 5 | J72: South | K72: 5 | L72: Matthew P. Thomas | M72: 24 | N72: 1 | O72: 32854 | P72: Online | Q72: Medium | R72: 20 | S72: Debit Card | T72: Miami | U72: 1100 | V72: Summer Sale | X72: =UPPER(C72) -> SAMSUNG GALAXY NOTE 20 | Y72: =LOWER(X72) -> samsung galaxy note 20 | Z72: =PROPER(Y72) -> Samsung Galaxy Note 20 | AA72: =IF(K72>=0.15*100,"High Discount","Low Discount") -> Low Discount
B75: Question 2
B77: You are given an Excel file containing raw and unfiltered hospital data. The dataset includes various details about patients, doctors, treatments, and related information.
B78: Your task is to clean, organize, and analyze the data to extract meaningful insights. Specifically, you need to:
B81: Data Cleaning and Formatting | G81: Answers
G82: Data cleaning
B83: Identify and correct the formatting inconsistencies in the "Treatment Date" and "Payment Status" columns. | H83: 1-A | I83: by using find/replace FN
B84: Standardize the phone number format across all entries. | H84: 1-B | I84: TEXT(VALUE(SUBSTITUTE(R154, "-", "")), "(000) 000-0000")
B85: Remove any duplicate records in the dataset. | H85: 1-C | I85: no duplicate
G86: Data analysis
B87: Data Analysis | H87: 2-A | I87: =SUMIF('FUNCTIONS PRACTICE'!$O$149:$O$210,"paid",'FUNCTIONS PRACTICE'!$K$149:$K$210) -> 23010
H88: 2-b | I88: =ROUNDUP(AVERAGE('FUNCTIONS PRACTICE'!$D$149:$D$210),1) -> 41.5
B89: Calculate the total revenue generated by paid treatments. | H89: 2-c
B90: Determine the average age of patients based on their date of birth. | G90: advanced queries
B91: Identify the most common medical issue treated at the hospital. | H91: 3-A
H92: 3-B | I92: =
B93: Advanced Queries | H93: 3-c | I93: REPORT
I94: status | J94: count | K94: percentage
B95: List all patients who have pending payments and the total amount they owe. | I95: Approved | J95: =COUNTIF(V149:V210,"approved") -> 31 | K95: =J95/62*100 -> 50
B96: Find the doctor who treated the most patients and list the number of patients treated. | I96: Pending | J96: =COUNTIF(V150:V211,"pending") -> 21 | K96: =ROUNDUP(J96/62*100,2) -> 33.88
B97: Generate a report of treatments categorized by their approval status (Approved, Pending, Denied). | I97: Denied | J97: =COUNTIF(V151:V212,"denied") -> 10 | K97: =ROUNDUP(J97/62*100,2) -> 16.13
G98: Data correlation
H99: 4-A | I99: cell location X153
B100: Data Correlation | H100: 4-B | I100: cell location AA
H101: 4-c
B102: Analyze the correlation between patient age and the cost of treatment. | G102: Pred/ comp Analysis
B103: Investigate if there is a pattern between certain doctors and the types of medical issues they treat. | H103: 5-A
B104: Examine the relationship between payment status and insurance provider. | H104: 5-B
H105: 5-C
B106: Predictive Analysis | H106: 5-D
H107: 5-E
B108: Predict the likelihood of payment status being "Paid" based on treatment cost and insurance provider. | H108: 5-F
B109: Estimate the expected revenue for the next month based on current trends.
...

Sheet POWER QUERY
B3: 11 MODULE
B5: POWER QUERY | K5: Points to be Noted
K7: data - new Query - select data from it
B8: Name | C8: Email | D8: Course | E8: Registration Date | F8: Fee Paid | G8: Name ID | H8: Session Start | I8: Payment Status | K8: I transform this data usiing power query
B9: Hailey Antcliff | C9: Hailey_Antcliff9757@yahoo.audio | D9: Leadership | E9: 44909 | F9: 500 | G9: HaileyA | H9: 44958 | I9: Full Payment
B10: Harvey Reyes | C10: Harvey_Reyes9354@voylg.directory | D10: Analytics | E10: 44925 | F10: 500 | G10: HarveyR | H10: 45017 | I10: Full Payment
B11: Carina Stubbs | C11: Carina_Stubbs8509@jh02o.org | D11: Accounting | E11: 44899 | F11: 500 | G11: CarinaS | H11: 44958 | I11: Full Payment
B12: Ramon Redden | C12: Ramon_Redden905@1kmd3.club | D12: Design and technology | E12: 44902 | F12: 500 | G12: RamonR | H12: 44958 | I12: Full Payment
B13: Matt Ashley | C13: Matt_Ashley6946@jh02o.info | D13: Analytics | E13: 44925 | F13: 100 | G13: MattA | H13: 45017 | I13: Half Payment
B14: Ronald Newton | C14: Ronald_Newton1403@1kmd3.com | D14: Design and technology | E14: 44917 | F14: 500 | G14: RonaldN | H14: 45017 | I14: Full Payment
B15: Jack Hobbs | C15: Jack_Hobbs4073@evyvh.auction | D15: Design and technology | E15: 44902 | F15: 500 | G15: JackH | H15: 44958 | I15: Full Payment
B16: Elena Shelton | C16: Elena_Shelton5238@karnv.org | D16: Analytics | E16: 44897 | F16: 500 | G16: ElenaS | H16: 44958 | I16: Full Payment
B17: Tom Alldridge | C17: Tom_Alldridge5905@gkvds.property | D17: Analytics | E17: 44905 | F17: 500 | G17: TomA | H17: 44958 | I17: Full Payment
B18: Henry Edmonds | C18: Henry_Edmonds4807@dbxli.store | D18: Analytics | E18: 44916 | F18: 500 | G18: HenryE | H18: 45017 | I18: Full Payment | K18: when we talk about Dashboard
B19: Jack Hudson | C19: Jack_Hudson8090@yafr7.audio | D19: Leadership | E19: 44921 | F19: 250 | G19: JackH | H19: 45017 | I19: Half Payment | K19: Consult Requirement with client
B20: Hadley Brown | C20: Hadley_Brown7577@xqj6f.business | D20: Leadership | E20: 44912 | F20: 500 | G20: HadleyB | H20: 45017 | I20: Full Payment | K20: decide design
B21: Carrie Simpson | C21: Carrie_Simpson7773@qu9ml.catering | D21: Analytics | E21: 44910 | F21: 250 | G21: CarrieS | H21: 45017 | I21: Half Payment | K21: data sources
B22: Harvey Bell | C22: Harvey_Bell7932@bu2lo.website | D22: Analytics | E22: 44898 | F22: 500 | G22: HarveyB | H22: 44958 | I22: Full Payment | K22: create first cut/Draft
B23: Barney Morris | C23: Barney_Morris5647@hepmv.autos | D23: Analytics | E23: 44919 | F23: 500 | G23: BarneyM | H23: 45017 | I23: Full Payment | K23: changes as per feedback and quality check
B24: Caydence Fisher | C24: Caydence_Fisher2480@bcfhs.store | D24: Leadership | E24: 44923 | F24: 500 | G24: CaydenceF | H24: 45017 | I24: Full Payment | K24: go live date
B25: Denny Bell | C25: Denny_Bell8404@cke3u.property | D25: Accounting | E25: 44911 | F25: 250 | G25: DennyB | H25: 45017 | I25: Half Payment | K25: Sop
B26: Nicole Norton | C26: Nicole_Norton7231@avn7d.zone | D26: Analytics | E26: 44918 | F26: 250 | G26: NicoleN | H26: 45017 | I26: Half Payment
B27: Daria Little | C27: Daria_Little6096@3wbkp.app | D27: Design and technology | E27: 44921 | F27: 250 | G27: DariaL | H27: 45017 | I27: Half Payment
B28: Lindsay Taylor | C28: Lindsay_Taylor7452@kyb7t.com | D28: Leadership | E28: 44898 | F28: 100 | G28: LindsayT | H28: 44958 | I28: Half Payment
B29: Mason Davies | C29: Mason_Davies1960@kyb7t.software | D29: Analytics | E29: 44913 | F29: 500 | G29: MasonD | H29: 45017 | I29: Full Payment
B30: Phoebe Morrison | C30: Phoebe_Morrison8611@xtwt3.store | D30: Design and technology | E30: 44915 | F30: 500 | G30: PhoebeM | H30: 45017 | I30: Full Payment
B31: Nate Thornton | C31: Nate_Thornton707@iaart.us | D31: Design and technology | E31: 44922 | F31: 100 | G31: NateT | H31: 45017 | I31: Half Payment
B32: Hayden Nanton | C32: Hayden_Nanton4520@yafr7.solutions | D32: Leadership | E32: 44905 | F32: 100 | G32: HaydenN | H32: 44958 | I32: Half Payment
B33: Evie Robe | C33: Evie_Robe9866@yahoo.mobi | D33: Analytics | E33: 44919 | F33: 100 | G33: EvieR | H33: 45017 | I33: Half Payment
B34: Mike Hunter | C34: Mike_Hunter6868@gkvds.digital | D34: Accounting | E34: 44922 | F34: 100 | G34: MikeH | H34: 45017 | I34: Half Payment
B35: Marilyn Jackson | C35: Marilyn_Jackson8632@gnjps.media | D35: Leadership | E35: 44903 | F35: 100 | G35: MarilynJ | H35: 44958 | I35: Half Payment
B36: Sloane Snell | C36: Sloane_Snell336@yahoo.page | D36: Analytics | E36: 44921 | F36: 250 | G36: SloaneS | H36: 45017 | I36: Half Payment
B37: Alessia Mcneill | C37: Alessia_Mcneill3403@bcfhs.services | D37: Design and technology | E37: 44908 | F37: 500 | G37: AlessiaM | H37: 44958 | I37: Full Payment
... B73: Elena Shelton | C73: Elena_Shelton5238@karnv.org | D73: Analytics | E73: 44897 | F73: 500 | G73: ElenaS | H73: 44958 | I73: Full Payment
